Workbook

Sheet START HERE
A1: FPL 2026/27 — Decision & Planning Workbook
A3: Purpose | B3: A transparent, formula-driven framework for weekly FPL decisions: player projection, fixture-adjusted value, minutes risk, captaincy, transfers, chips and review.
A4: Important | B4: The workbook does not pretend to know future points. It turns your inputs into a consistent decision process. Update the input data each week.
A5: Season | B5: 2026/27
A7: Weekly workflow
A8: 1. Update Player Pool with the latest player statistics, prices, minutes/start likelihood and next-fixture information.
A9: 2. Update the GW Planner with your squad, fixture difficulty and projected minutes for the next 6–8 Gameweeks.
A10: 3. Review Dashboard: xP, xP/£m, fixture-adjusted xP, minutes risk and captain score.
A11: 4. Use Transfers to compare OUT vs IN using projected gain, fixture run and transfer cost.
A12: 5. Check chips only when the underlying squad/fixture opportunity is materially stronger than a normal week.
A13: 6. Lock the XI, captain, vice-captain and bench order before the deadline. Then record the actual result and review your assumptions.
A16: Official-rule anchors used in this workbook
A17: Budget | B17: £100.0m initial squad budget
A18: Squad | B18: 15 players: 2 GK, 5 DEF, 5 MID, 3 FWD
A19: Club limit | B19: Maximum 3 players from one Premier League club
A20: Free transfers | B20: 1 per Gameweek; saved transfers can accumulate up to 5
A21: Extra transfer | B21: −4 points per additional transfer
A22: Chips | B22: 2026/27: Wildcard, Free Hit, Triple Captain and Bench Boost twice each
A23: First chip set | B23: Must be used by the Gameweek 19 deadline
A24: Deadline | B24: 90 minutes before the first kick-off of the Gameweek
A25: Advanced version additions
A26: Weekly Input means you update one consolidated row per player rather than re-entering the same statistics across multiple sheets.
A27: 8-GW engine projects each player across eight future Gameweeks and discounts further-out weeks slightly.
A28: Transfer EV compares both 6GW and 8GW expected value and explicitly subtracts the transfer hit.
A29: Captaincy uses a relative probability distribution based on attacking ceiling, minutes confidence and fixture.
A30: Chip Planner forces you to score the opportunity instead of using a chip simply because a Double Gameweek exists.
A31: Weekly Review lets you calibrate the model without overreacting to one-week variance.

Sheet SETTINGS
A1: Parameter | B1: Value | C1: How it is used
A2: Base appearance xP | B2: 2 | C2: Baseline points per appearance before attacking/defensive/bonus contributions
A3: Goal weight GK | B3: 10 | C3: FPL points per GK goal
A4: Goal weight DEF | B4: 6 | C4: FPL points per defender goal
A5: Goal weight MID | B5: 5 | C5: FPL points per midfielder goal
A6: Goal weight FWD | B6: 4 | C6: FPL points per forward goal
A7: Assist weight | B7: 3 | C7: FPL points per assist
A8: CS weight GK/DEF | B8: 4 | C8: FPL points for a goalkeeper/defender clean sheet
A9: CS weight MID | B9: 1 | C9: FPL points for a midfielder clean sheet
A10: Save points per 3 saves | B10: 1 | C10: Goalkeeper save scoring
A11: Defensive contribution points | B11: 2 | C11: Points awarded at the threshold
A12: xG regression factor | B12: 0.65 | C12: Blends expected goals with actual goals to avoid overreacting to finishing streaks
A13: xA regression factor | B13: 0.65 | C13: Blends expected assists with actual assists
... A18: Captain ceiling weight | B18: 0.1 | C18: Weight on attacking ceiling for captain score
A20: Advanced model settings
A21: Projection horizon | B21: 8 | C21: Number of future Gameweeks projected in the 8-GW engine.
A22: Minutes prior weight | B22: 0.35 | C22: Weight assigned to historical minutes/start rate.
A23: Minutes recent weight | B23: 0.65 | C23: Weight assigned to recent minutes/start rate.
A24: xG weight | B24: 0.5 | C24: Share of attacking expectation from xG.
A25: xA weight | B25: 0.3 | C25: Share of attacking expectation from xA.
A26: Form weight (8GW) | B26: 0.2 | C26: Share of recent FPL points/90 in the projection.
A27: Fixture range | B27: 0.2 | C27: Fixture adjustment strength; deliberately modest.
A28: Rotation penalty max | B28: 0.3 | C28: Maximum projection penalty for uncertain minutes.
A29: Captain ceiling multiplier | B29: 1.25 | C29: Adds upside emphasis to captain candidates.
A30: Transfer horizon | B30: 6 | C30: Gameweeks used for transfer EV comparison.
A31: Hit cost | B31: 4 | C31: FPL points deducted per additional transfer.
A32: Sell-price haircut | B32: 0.5 | C32: Approximate treatment of selling value versus current price; editable.

Sheet PLAYER POOL
A1: Player | B1: Club | C1: Pos | D1: Price £m | E1: Ownership % | F1: Minutes last 6 | G1: Starts last 6 | H1: xG last 6 | I1: xA last 6 | J1: Goals last 6 | K1: Assists last 6 | L1: Shots last 6 | M1: Big chances last 6 | N1: Key passes last 6 | O1: Defensive contrib last 6 | P1: Projected minutes next GW | Q1: Start probability % | R1: Next fixture difficulty (1 easy–5 hard) | S1: Fixture multiplier | T1: xG/90 | U1: xA/90 | V1: xGI/90 | W1: Recent FPL pts/90 | X1: Underlying xP next GW | Y1: Fixture-adjusted xP | Z1: xP/£m | AA1: Minutes risk | AB1: Decision Score | AC1: Captain Score | AD1: Notes
S2: =IF(R2="","",1+(3-R2)*0.10) | T2: =IFERROR(H2/F2*90,0) | U2: =IFERROR(I2/F2*90,0) | V2: =T2+U2 | W2: =IFERROR((H2*5+I2*3+J2*0+K2*0)/F2,0) | X2: =IFERROR((2*(P2/90))+(T2/90*5)+(U2/90*3)+(O2/F2*2)+(W2*0.5),0) | Y2: =IF(X2="","",X2*S2*(P2/90)) | Z2: =IFERROR(Y2/D2,0) | AA2: =IF(P2="","",MAX(0,1-P2/90)) | AB2: =IFERROR(Y2*(1+0.20*W2+0.15*Z2)*(1-AA2*0.75),0) | AC2: =IFERROR((T2+U2)*S2*(P2/90)*(1+0.25*(3-R2)),0)
S3: =IF(R3="","",1+(3-R3)*0.10) | T3: =IFERROR(H3/F3*90,0) | U3: =IFERROR(I3/F3*90,0) | V3: =T3+U3 | W3: =IFERROR((H3*5+I3*3+J3*0+K3*0)/F3,0) | X3: =IFERROR((2*(P3/90))+(T3/90*5)+(U3/90*3)+(O3/F3*2)+(W3*0.5),0) | Y3: =IF(X3="","",X3*S3*(P3/90)) | Z3: =IFERROR(Y3/D3,0) | AA3: =IF(P3="","",MAX(0,1-P3/90)) | AB3: =IFERROR(Y3*(1+0.20*W3+0.15*Z3)*(1-AA3*0.75),0) | AC3: =IFERROR((T3+U3)*S3*(P3/90)*(1+0.25*(3-R3)),0)
S4: =IF(R4="","",1+(3-R4)*0.10) | T4: =IFERROR(H4/F4*90,0) | U4: =IFERROR(I4/F4*90,0) | V4: =T4+U4 | W4: =IFERROR((H4*5+I4*3+J4*0+K4*0)/F4,0) | X4: =IFERROR((2*(P4/90))+(T4/90*5)+(U4/90*3)+(O4/F4*2)+(W4*0.5),0) | Y4: =IF(X4="","",X4*S4*(P4/90)) | Z4: =IFERROR(Y4/D4,0) | AA4: =IF(P4="","",MAX(0,1-P4/90)) | AB4: =IFERROR(Y4*(1+0.20*W4+0.15*Z4)*(1-AA4*0.75),0) | AC4: =IFERROR((T4+U4)*S4*(P4/90)*(1+0.25*(3-R4)),0)
S5: =IF(R5="","",1+(3-R5)*0.10) | T5: =IFERROR(H5/F5*90,0) | U5: =IFERROR(I5/F5*90,0) | V5: =T5+U5 | W5: =IFERROR((H5*5+I5*3+J5*0+K5*0)/F5,0) | X5: =IFERROR((2*(P5/90))+(T5/90*5)+(U5/90*3)+(O5/F5*2)+(W5*0.5),0) | Y5: =IF(X5="","",X5*S5*(P5/90)) | Z5: =IFERROR(Y5/D5,0) | AA5: =IF(P5="","",MAX(0,1-P5/90)) | AB5: =IFERROR(Y5*(1+0.20*W5+0.15*Z5)*(1-AA5*0.75),0) | AC5: =IFERROR((T5+U5)*S5*(P5/90)*(1+0.25*(3-R5)),0)
S6: =IF(R6="","",1+(3-R6)*0.10) | T6: =IFERROR(H6/F6*90,0) | U6: =IFERROR(I6/F6*90,0) | V6: =T6+U6 | W6: =IFERROR((H6*5+I6*3+J6*0+K6*0)/F6,0) | X6: =IFERROR((2*(P6/90))+(T6/90*5)+(U6/90*3)+(O6/F6*2)+(W6*0.5),0) | Y6: =IF(X6="","",X6*S6*(P6/90)) | Z6: =IFERROR(Y6/D6,0) | AA6: =IF(P6="","",MAX(0,1-P6/90)) | AB6: =IFERROR(Y6*(1+0.20*W6+0.15*Z6)*(1-AA6*0.75),0) | AC6: =IFERROR((T6+U6)*S6*(P6/90)*(1+0.25*(3-R6)),0)
S7: =IF(R7="","",1+(3-R7)*0.10) | T7: =IFERROR(H7/F7*90,0) | U7: =IFERROR(I7/F7*90,0) | V7: =T7+U7 | W7: =IFERROR((H7*5+I7*3+J7*0+K7*0)/F7,0) | X7: =IFERROR((2*(P7/90))+(T7/90*5)+(U7/90*3)+(O7/F7*2)+(W7*0.5),0) | Y7: =IF(X7="","",X7*S7*(P7/90)) | Z7: =IFERROR(Y7/D7,0) | AA7: =IF(P7="","",MAX(0,1-P7/90)) | AB7: =IFERROR(Y7*(1+0.20*W7+0.15*Z7)*(1-AA7*0.75),0) | AC7: =IFERROR((T7+U7)*S7*(P7/90)*(1+0.25*(3-R7)),0)
S8: =IF(R8="","",1+(3-R8)*0.10) | T8: =IFERROR(H8/F8*90,0) | U8: =IFERROR(I8/F8*90,0) | V8: =T8+U8 | W8: =IFERROR((H8*5+I8*3+J8*0+K8*0)/F8,0) | X8: =IFERROR((2*(P8/90))+(T8/90*5)+(U8/90*3)+(O8/F8*2)+(W8*0.5),0) | Y8: =IF(X8="","",X8*S8*(P8/90)) | Z8: =IFERROR(Y8/D8,0) | AA8: =IF(P8="","",MAX(0,1-P8/90)) | AB8: =IFERROR(Y8*(1+0.20*W8+0.15*Z8)*(1-AA8*0.75),0) | AC8: =IFERROR((T8+U8)*S8*(P8/90)*(1+0.25*(3-R8)),0)
S9: =IF(R9="","",1+(3-R9)*0.10) | T9: =IFERROR(H9/F9*90,0) | U9: =IFERROR(I9/F9*90,0) | V9: =T9+U9 | W9: =IFERROR((H9*5+I9*3+J9*0+K9*0)/F9,0) | X9: =IFERROR((2*(P9/90))+(T9/90*5)+(U9/90*3)+(O9/F9*2)+(W9*0.5),0) | Y9: =IF(X9="","",X9*S9*(P9/90)) | Z9: =IFERROR(Y9/D9,0) | AA9: =IF(P9="","",MAX(0,1-P9/90)) | AB9: =IFERROR(Y9*(1+0.20*W9+0.15*Z9)*(1-AA9*0.75),0) | AC9: =IFERROR((T9+U9)*S9*(P9/90)*(1+0.25*(3-R9)),0)
S10: =IF(R10="","",1+(3-R10)*0.10) | T10: =IFERROR(H10/F10*90,0) | U10: =IFERROR(I10/F10*90,0) | V10: =T10+U10 | W10: =IFERROR((H10*5+I10*3+J10*0+K10*0)/F10,0) | X10: =IFERROR((2*(P10/90))+(T10/90*5)+(U10/90*3)+(O10/F10*2)+(W10*0.5),0) | Y10: =IF(X10="","",X10*S10*(P10/90)) | Z10: =IFERROR(Y10/D10,0) | AA10: =IF(P10="","",MAX(0,1-P10/90)) | AB10: =IFERROR(Y10*(1+0.20*W10+0.15*Z10)*(1-AA10*0.75),0) | AC10: =IFERROR((T10+U10)*S10*(P10/90)*(1+0.25*(3-R10)),0)
S11: =IF(R11="","",1+(3-R11)*0.10) | T11: =IFERROR(H11/F11*90,0) | U11: =IFERROR(I11/F11*90,0) | V11: =T11+U11 | W11: =IFERROR((H11*5+I11*3+J11*0+K11*0)/F11,0) | X11: =IFERROR((2*(P11/90))+(T11/90*5)+(U11/90*3)+(O11/F11*2)+(W11*0.5),0) | Y11: =IF(X11="","",X11*S11*(P11/90)) | Z11: =IFERROR(Y11/D11,0) | AA11: =IF(P11="","",MAX(0,1-P11/90)) | AB11: =IFERROR(Y11*(1+0.20*W11+0.15*Z11)*(1-AA11*0.75),0) | AC11: =IFERROR((T11+U11)*S11*(P11/90)*(1+0.25*(3-R11)),0)
S12: =IF(R12="","",1+(3-R12)*0.10) | T12: =IFERROR(H12/F12*90,0) | U12: =IFERROR(I12/F12*90,0) | V12: =T12+U12 | W12: =IFERROR((H12*5+I12*3+J12*0+K12*0)/F12,0) | X12: =IFERROR((2*(P12/90))+(T12/90*5)+(U12/90*3)+(O12/F12*2)+(W12*0.5),0) | Y12: =IF(X12="","",X12*S12*(P12/90)) | Z12: =IFERROR(Y12/D12,0) | AA12: =IF(P12="","",MAX(0,1-P12/90)) | AB12: =IFERROR(Y12*(1+0.20*W12+0.15*Z12)*(1-AA12*0.75),0) | AC12: =IFERROR((T12+U12)*S12*(P12/90)*(1+0.25*(3-R12)),0)
S13: =IF(R13="","",1+(3-R13)*0.10) | T13: =IFERROR(H13/F13*90,0) | U13: =IFERROR(I13/F13*90,0) | V13: =T13+U13 | W13: =IFERROR((H13*5+I13*3+J13*0+K13*0)/F13,0) | X13: =IFERROR((2*(P13/90))+(T13/90*5)+(U13/90*3)+(O13/F13*2)+(W13*0.5),0) | Y13: =IF(X13="","",X13*S13*(P13/90)) | Z13: =IFERROR(Y13/D13,0) | AA13: =IF(P13="","",MAX(0,1-P13/90)) | AB13: =IFERROR(Y13*(1+0.20*W13+0.15*Z13)*(1-AA13*0.75),0) | AC13: =IFERROR((T13+U13)*S13*(P13/90)*(1+0.25*(3-R13)),0)
... S201: =IF(R201="","",1+(3-R201)*0.10) | T201: =IFERROR(H201/F201*90,0) | U201: =IFERROR(I201/F201*90,0) | V201: =T201+U201 | W201: =IFERROR((H201*5+I201*3+J201*0+K201*0)/F201,0) | X201: =IFERROR((2*(P201/90))+(T201/90*5)+(U201/90*3)+(O201/F201*2)+(W201*0.5),0) | Y201: =IF(X201="","",X201*S201*(P201/90)) | Z201: =IFERROR(Y201/D201,0) | AA201: =IF(P201="","",MAX(0,1-P201/90)) | AB201: =IFERROR(Y201*(1+0.20*W201+0.15*Z201)*(1-AA201*0.75),0) | AC201: =IFERROR((T201+U201)*S201*(P201/90)*(1+0.25*(3-R201)),0)

Sheet GW PLANNER
A1: GW | B1: Player | C1: Club | D1: Pos | E1: Price £m | F1: Starter? | G1: Captain? | H1: Fixture difficulty | I1: Projected minutes | J1: xP | K1: Fixture-adjusted xP | L1: Expected points contribution | M1: Bench order | N1: Actual points | O1: Variance | P1: Review note
J2: =IFERROR(XLOOKUP(B2,'PLAYER POOL'!A:A,'PLAYER POOL'!X:X),"") | K2: =IFERROR(XLOOKUP(B2,'PLAYER POOL'!A:A,'PLAYER POOL'!Y:Y),"") | L2: =IF(F2="Yes",K2*IF(G2="Yes",2,1),0) | O2: =IF(N2="","",N2-L2)
J3: =IFERROR(XLOOKUP(B3,'PLAYER POOL'!A:A,'PLAYER POOL'!X:X),"") | K3: =IFERROR(XLOOKUP(B3,'PLAYER POOL'!A:A,'PLAYER POOL'!Y:Y),"") | L3: =IF(F3="Yes",K3*IF(G3="Yes",2,1),0) | O3: =IF(N3="","",N3-L3)
J4: =IFERROR(XLOOKUP(B4,'PLAYER POOL'!A:A,'PLAYER POOL'!X:X),"") | K4: =IFERROR(XLOOKUP(B4,'PLAYER POOL'!A:A,'PLAYER POOL'!Y:Y),"") | L4: =IF(F4="Yes",K4*IF(G4="Yes",2,1),0) | O4: =IF(N4="","",N4-L4)
J5: =IFERROR(XLOOKUP(B5,'PLAYER POOL'!A:A,'PLAYER POOL'!X:X),"") | K5: =IFERROR(XLOOKUP(B5,'PLAYER POOL'!A:A,'PLAYER POOL'!Y:Y),"") | L5: =IF(F5="Yes",K5*IF(G5="Yes",2,1),0) | O5: =IF(N5="","",N5-L5)
J6: =IFERROR(XLOOKUP(B6,'PLAYER POOL'!A:A,'PLAYER POOL'!X:X),"") | K6: =IFERROR(XLOOKUP(B6,'PLAYER POOL'!A:A,'PLAYER POOL'!Y:Y),"") | L6: =IF(F6="Yes",K6*IF(G6="Yes",2,1),0) | O6: =IF(N6="","",N6-L6)
J7: =IFERROR(XLOOKUP(B7,'PLAYER POOL'!A:A,'PLAYER POOL'!X:X),"") | K7: =IFERROR(XLOOKUP(B7,'PLAYER POOL'!A:A,'PLAYER POOL'!Y:Y),"") | L7: =IF(F7="Yes",K7*IF(G7="Yes",2,1),0) | O7: =IF(N7="","",N7-L7)
J8: =IFERROR(XLOOKUP(B8,'PLAYER POOL'!A:A,'PLAYER POOL'!X:X),"") | K8: =IFERROR(XLOOKUP(B8,'PLAYER POOL'!A:A,'PLAYER POOL'!Y:Y),"") | L8: =IF(F8="Yes",K8*IF(G8="Yes",2,1),0) | O8: =IF(N8="","",N8-L8)
J9: =IFERROR(XLOOKUP(B9,'PLAYER POOL'!A:A,'PLAYER POOL'!X:X),"") | K9: =IFERROR(XLOOKUP(B9,'PLAYER POOL'!A:A,'PLAYER POOL'!Y:Y),"") | L9: =IF(F9="Yes",K9*IF(G9="Yes",2,1),0) | O9: =IF(N9="","",N9-L9)
J10: =IFERROR(XLOOKUP(B10,'PLAYER POOL'!A:A,'PLAYER POOL'!X:X),"") | K10: =IFERROR(XLOOKUP(B10,'PLAYER POOL'!A:A,'PLAYER POOL'!Y:Y),"") | L10: =IF(F10="Yes",K10*IF(G10="Yes",2,1),0) | O10: =IF(N10="","",N10-L10)
J11: =IFERROR(XLOOKUP(B11,'PLAYER POOL'!A:A,'PLAYER POOL'!X:X),"") | K11: =IFERROR(XLOOKUP(B11,'PLAYER POOL'!A:A,'PLAYER POOL'!Y:Y),"") | L11: =IF(F11="Yes",K11*IF(G11="Yes",2,1),0) | O11: =IF(N11="","",N11-L11)
J12: =IFERROR(XLOOKUP(B12,'PLAYER POOL'!A:A,'PLAYER POOL'!X:X),"") | K12: =IFERROR(XLOOKUP(B12,'PLAYER POOL'!A:A,'PLAYER POOL'!Y:Y),"") | L12: =IF(F12="Yes",K12*IF(G12="Yes",2,1),0) | O12: =IF(N12="","",N12-L12)
J13: =IFERROR(XLOOKUP(B13,'PLAYER POOL'!A:A,'PLAYER POOL'!X:X),"") | K13: =IFERROR(XLOOKUP(B13,'PLAYER POOL'!A:A,'PLAYER POOL'!Y:Y),"") | L13: =IF(F13="Yes",K13*IF(G13="Yes",2,1),0) | O13: =IF(N13="","",N13-L13)
... J301: =IFERROR(XLOOKUP(B301,'PLAYER POOL'!A:A,'PLAYER POOL'!X:X),"") | K301: =IFERROR(XLOOKUP(B301,'PLAYER POOL'!A:A,'PLAYER POOL'!Y:Y),"") | L301: =IF(F301="Yes",K301*IF(G301="Yes",2,1),0) | O301: =IF(N301="","",N301-L301)

Sheet TRANSFERS
A1: GW | B1: OUT player | C1: OUT xP | D1: IN player | E1: IN xP | F1: Projected gain | G1: Transfer cost | H1: Net gain | I1: Price delta £m | J1: Fixture run note | K1: Decision
C2: =IFERROR(XLOOKUP(B2,'PLAYER POOL'!A:A,'PLAYER POOL'!Y:Y),0) | E2: =IFERROR(XLOOKUP(D2,'PLAYER POOL'!A:A,'PLAYER POOL'!Y:Y),0) | F2: =E2-C2 | G2: 0 | H2: =F2-G2 | K2: =IF(H2>=1,"Positive edge","No clear edge")
C3: =IFERROR(XLOOKUP(B3,'PLAYER POOL'!A:A,'PLAYER POOL'!Y:Y),0) | E3: =IFERROR(XLOOKUP(D3,'PLAYER POOL'!A:A,'PLAYER POOL'!Y:Y),0) | F3: =E3-C3 | G3: 0 | H3: =F3-G3 | K3: =IF(H3>=1,"Positive edge","No clear edge")
C4: =IFERROR(XLOOKUP(B4,'PLAYER POOL'!A:A,'PLAYER POOL'!Y:Y),0) | E4: =IFERROR(XLOOKUP(D4,'PLAYER POOL'!A:A,'PLAYER POOL'!Y:Y),0) | F4: =E4-C4 | G4: 0 | H4: =F4-G4 | K4: =IF(H4>=1,"Positive edge","No clear edge")
C5: =IFERROR(XLOOKUP(B5,'PLAYER POOL'!A:A,'PLAYER POOL'!Y:Y),0) | E5: =IFERROR(XLOOKUP(D5,'PLAYER POOL'!A:A,'PLAYER POOL'!Y:Y),0) | F5: =E5-C5 | G5: 0 | H5: =F5-G5 | K5: =IF(H5>=1,"Positive edge","No clear edge")
C6: =IFERROR(XLOOKUP(B6,'PLAYER POOL'!A:A,'PLAYER POOL'!Y:Y),0) | E6: =IFERROR(XLOOKUP(D6,'PLAYER POOL'!A:A,'PLAYER POOL'!Y:Y),0) | F6: =E6-C6 | G6: 0 | H6: =F6-G6 | K6: =IF(H6>=1,"Positive edge","No clear edge")
C7: =IFERROR(XLOOKUP(B7,'PLAYER POOL'!A:A,'PLAYER POOL'!Y:Y),0) | E7: =IFERROR(XLOOKUP(D7,'PLAYER POOL'!A:A,'PLAYER POOL'!Y:Y),0) | F7: =E7-C7 | G7: 0 | H7: =F7-G7 | K7: =IF(H7>=1,"Positive edge","No clear edge")
C8: =IFERROR(XLOOKUP(B8,'PLAYER POOL'!A:A,'PLAYER POOL'!Y:Y),0) | E8: =IFERROR(XLOOKUP(D8,'PLAYER POOL'!A:A,'PLAYER POOL'!Y:Y),0) | F8: =E8-C8 | G8: 0 | H8: =F8-G8 | K8: =IF(H8>=1,"Positive edge","No clear edge")
C9: =IFERROR(XLOOKUP(B9,'PLAYER POOL'!A:A,'PLAYER POOL'!Y:Y),0) | E9: =IFERROR(XLOOKUP(D9,'PLAYER POOL'!A:A,'PLAYER POOL'!Y:Y),0) | F9: =E9-C9 | G9: 0 | H9: =F9-G9 | K9: =IF(H9>=1,"Positive edge","No clear edge")
C10: =IFERROR(XLOOKUP(B10,'PLAYER POOL'!A:A,'PLAYER POOL'!Y:Y),0) | E10: =IFERROR(XLOOKUP(D10,'PLAYER POOL'!A:A,'PLAYER POOL'!Y:Y),0) | F10: =E10-C10 | G10: 0 | H10: =F10-G10 | K10: =IF(H10>=1,"Positive edge","No clear edge")
C11: =IFERROR(XLOOKUP(B11,'PLAYER POOL'!A:A,'PLAYER POOL'!Y:Y),0) | E11: =IFERROR(XLOOKUP(D11,'PLAYER POOL'!A:A,'PLAYER POOL'!Y:Y),0) | F11: =E11-C11 | G11: 0 | H11: =F11-G11 | K11: =IF(H11>=1,"Positive edge","No clear edge")
C12: =IFERROR(XLOOKUP(B12,'PLAYER POOL'!A:A,'PLAYER POOL'!Y:Y),0) | E12: =IFERROR(XLOOKUP(D12,'PLAYER POOL'!A:A,'PLAYER POOL'!Y:Y),0) | F12: =E12-C12 | G12: 0 | H12: =F12-G12 | K12: =IF(H12>=1,"Positive edge","No clear edge")
C13: =IFERROR(XLOOKUP(B13,'PLAYER POOL'!A:A,'PLAYER POOL'!Y:Y),0) | E13: =IFERROR(XLOOKUP(D13,'PLAYER POOL'!A:A,'PLAYER POOL'!Y:Y),0) | F13: =E13-C13 | G13: 0 | H13: =F13-G13 | K13: =IF(H13>=1,"Positive edge","No clear edge")
... C101: =IFERROR(XLOOKUP(B101,'PLAYER POOL'!A:A,'PLAYER POOL'!Y:Y),0) | E101: =IFERROR(XLOOKUP(D101,'PLAYER POOL'!A:A,'PLAYER POOL'!Y:Y),0) | F101: =E101-C101 | G101: 0 | H101: =F101-G101 | K101: =IF(H101>=1,"Positive edge","No clear edge")
A105: How to use transfer cost | B105: Enter 0 for a free transfer. Enter 4 per extra transfer you expect to take. The workbook deliberately keeps this manual because the actual cost depends on your saved free transfers.

Sheet TEAM
A1: Slot | B1: Player | C1: Club | D1: Pos | E1: Purchase price £m | F1: Current price £m | G1: Selling price £m | H1: GW xP | I1: Starter? | J1: Captain? | K1: Bench order
A2: GK1 | C2: =IFERROR(XLOOKUP(B2,'PLAYER POOL'!A:A,'PLAYER POOL'!B:B),"") | D2: =IFERROR(XLOOKUP(B2,'PLAYER POOL'!A:A,'PLAYER POOL'!C:C),"") | F2: =IFERROR(XLOOKUP(B2,'PLAYER POOL'!A:A,'PLAYER POOL'!D:D),"") | G2: =IFERROR(E2+MAX(0,F2-E2)/2,0) | H2: =IFERROR(XLOOKUP(B2,'PLAYER POOL'!A:A,'PLAYER POOL'!Y:Y),0)
A3: GK2 | C3: =IFERROR(XLOOKUP(B3,'PLAYER POOL'!A:A,'PLAYER POOL'!B:B),"") | D3: =IFERROR(XLOOKUP(B3,'PLAYER POOL'!A:A,'PLAYER POOL'!C:C),"") | F3: =IFERROR(XLOOKUP(B3,'PLAYER POOL'!A:A,'PLAYER POOL'!D:D),"") | G3: =IFERROR(E3+MAX(0,F3-E3)/2,0) | H3: =IFERROR(XLOOKUP(B3,'PLAYER POOL'!A:A,'PLAYER POOL'!Y:Y),0)
A4: DEF1 | C4: =IFERROR(XLOOKUP(B4,'PLAYER POOL'!A:A,'PLAYER POOL'!B:B),"") | D4: =IFERROR(XLOOKUP(B4,'PLAYER POOL'!A:A,'PLAYER POOL'!C:C),"") | F4: =IFERROR(XLOOKUP(B4,'PLAYER POOL'!A:A,'PLAYER POOL'!D:D),"") | G4: =IFERROR(E4+MAX(0,F4-E4)/2,0) | H4: =IFERROR(XLOOKUP(B4,'PLAYER POOL'!A:A,'PLAYER POOL'!Y:Y),0)
A5: DEF2 | C5: =IFERROR(XLOOKUP(B5,'PLAYER POOL'!A:A,'PLAYER POOL'!B:B),"") | D5: =IFERROR(XLOOKUP(B5,'PLAYER POOL'!A:A,'PLAYER POOL'!C:C),"") | F5: =IFERROR(XLOOKUP(B5,'PLAYER POOL'!A:A,'PLAYER POOL'!D:D),"") | G5: =IFERROR(E5+MAX(0,F5-E5)/2,0) | H5: =IFERROR(XLOOKUP(B5,'PLAYER POOL'!A:A,'PLAYER POOL'!Y:Y),0)
A6: DEF3 | C6: =IFERROR(XLOOKUP(B6,'PLAYER POOL'!A:A,'PLAYER POOL'!B:B),"") | D6: =IFERROR(XLOOKUP(B6,'PLAYER POOL'!A:A,'PLAYER POOL'!C:C),"") | F6: =IFERROR(XLOOKUP(B6,'PLAYER POOL'!A:A,'PLAYER POOL'!D:D),"") | G6: =IFERROR(E6+MAX(0,F6-E6)/2,0) | H6: =IFERROR(XLOOKUP(B6,'PLAYER POOL'!A:A,'PLAYER POOL'!Y:Y),0)
A7: DEF4 | C7: =IFERROR(XLOOKUP(B7,'PLAYER POOL'!A:A,'PLAYER POOL'!B:B),"") | D7: =IFERROR(XLOOKUP(B7,'PLAYER POOL'!A:A,'PLAYER POOL'!C:C),"") | F7: =IFERROR(XLOOKUP(B7,'PLAYER POOL'!A:A,'PLAYER POOL'!D:D),"") | G7: =IFERROR(E7+MAX(0,F7-E7)/2,0) | H7: =IFERROR(XLOOKUP(B7,'PLAYER POOL'!A:A,'PLAYER POOL'!Y:Y),0)
A8: DEF5 | C8: =IFERROR(XLOOKUP(B8,'PLAYER POOL'!A:A,'PLAYER POOL'!B:B),"") | D8: =IFERROR(XLOOKUP(B8,'PLAYER POOL'!A:A,'PLAYER POOL'!C:C),"") | F8: =IFERROR(XLOOKUP(B8,'PLAYER POOL'!A:A,'PLAYER POOL'!D:D),"") | G8: =IFERROR(E8+MAX(0,F8-E8)/2,0) | H8: =IFERROR(XLOOKUP(B8,'PLAYER POOL'!A:A,'PLAYER POOL'!Y:Y),0)
A9: MID1 | C9: =IFERROR(XLOOKUP(B9,'PLAYER POOL'!A:A,'PLAYER POOL'!B:B),"") | D9: =IFERROR(XLOOKUP(B9,'PLAYER POOL'!A:A,'PLAYER POOL'!C:C),"") | F9: =IFERROR(XLOOKUP(B9,'PLAYER POOL'!A:A,'PLAYER POOL'!D:D),"") | G9: =IFERROR(E9+MAX(0,F9-E9)/2,0) | H9: =IFERROR(XLOOKUP(B9,'PLAYER POOL'!A:A,'PLAYER POOL'!Y:Y),0)
A10: MID2 | C10: =IFERROR(XLOOKUP(B10,'PLAYER POOL'!A:A,'PLAYER POOL'!B:B),"") | D10: =IFERROR(XLOOKUP(B10,'PLAYER POOL'!A:A,'PLAYER POOL'!C:C),"") | F10: =IFERROR(XLOOKUP(B10,'PLAYER POOL'!A:A,'PLAYER POOL'!D:D),"") | G10: =IFERROR(E10+MAX(0,F10-E10)/2,0) | H10: =IFERROR(XLOOKUP(B10,'PLAYER POOL'!A:A,'PLAYER POOL'!Y:Y),0)
A11: MID3 | C11: =IFERROR(XLOOKUP(B11,'PLAYER POOL'!A:A,'PLAYER POOL'!B:B),"") | D11: =IFERROR(XLOOKUP(B11,'PLAYER POOL'!A:A,'PLAYER POOL'!C:C),"") | F11: =IFERROR(XLOOKUP(B11,'PLAYER POOL'!A:A,'PLAYER POOL'!D:D),"") | G11: =IFERROR(E11+MAX(0,F11-E11)/2,0) | H11: =IFERROR(XLOOKUP(B11,'PLAYER POOL'!A:A,'PLAYER POOL'!Y:Y),0)
A12: MID4 | C12: =IFERROR(XLOOKUP(B12,'PLAYER POOL'!A:A,'PLAYER POOL'!B:B),"") | D12: =IFERROR(XLOOKUP(B12,'PLAYER POOL'!A:A,'PLAYER POOL'!C:C),"") | F12: =IFERROR(XLOOKUP(B12,'PLAYER POOL'!A:A,'PLAYER POOL'!D:D),"") | G12: =IFERROR(E12+MAX(0,F12-E12)/2,0) | H12: =IFERROR(XLOOKUP(B12,'PLAYER POOL'!A:A,'PLAYER POOL'!Y:Y),0)
A13: MID5 | C13: =IFERROR(XLOOKUP(B13,'PLAYER POOL'!A:A,'PLAYER POOL'!B:B),"") | D13: =IFERROR(XLOOKUP(B13,'PLAYER POOL'!A:A,'PLAYER POOL'!C:C),"") | F13: =IFERROR(XLOOKUP(B13,'PLAYER POOL'!A:A,'PLAYER POOL'!D:D),"") | G13: =IFERROR(E13+MAX(0,F13-E13)/2,0) | H13: =IFERROR(XLOOKUP(B13,'PLAYER POOL'!A:A,'PLAYER POOL'!Y:Y),0)
... A16: FWD3 | C16: =IFERROR(XLOOKUP(B16,'PLAYER POOL'!A:A,'PLAYER POOL'!B:B),"") | D16: =IFERROR(XLOOKUP(B16,'PLAYER POOL'!A:A,'PLAYER POOL'!C:C),"") | F16: =IFERROR(XLOOKUP(B16,'PLAYER POOL'!A:A,'PLAYER POOL'!D:D),"") | G16: =IFERROR(E16+MAX(0,F16-E16)/2,0) | H16: =IFERROR(XLOOKUP(B16,'PLAYER POOL'!A:A,'PLAYER POOL'!Y:Y),0)
A19: Team summary
A20: Squad value | B20: =SUM(F2:F16)
A21: Approx selling value | B21: =SUM(G2:G16)
A22: Projected GW points (XI only) | B22: =SUMIF(I2:I16,"Yes",H2:H16)+SUMIF(J2:J16,"Yes",H2:H16)
A23: Projected captaincy points | B23: =SUMIF(J2:J16,"Yes",H2:H16)

Sheet CHIPS
A1: Chip | B1: Half | C1: Status | D1: GW used | E1: Opportunity score | F1: Trigger / rationale | G1: Review
A2: Wildcard | B2: 1st | C2: Available
A3: Free Hit | B3: 1st | C3: Available
A4: Triple Captain | B4: 1st | C4: Available
A5: Bench Boost | B5: 1st | C5: Available
A6: Wildcard | B6: 2nd | C6: Available
A7: Free Hit | B7: 2nd | C7: Available
A8: Triple Captain | B8: 2nd | C8: Available
A9: Bench Boost | B9: 2nd | C9: Available

Sheet DASHBOARD
A1: FPL Decision Dashboard
A3: Squad value | B3: =TEAM!B20 | D3: Decision hierarchy
A4: Projected XI points | B4: =TEAM!B22 | D4: 1. Minutes first: a 6.5 xP player who may not start is often worse than a 5.8 xP secure starter.
A5: Projected captain points | B5: =TEAM!B23 | D5: 2. Projected points second: prefer repeatable opportunity (xG/xA, role, set pieces, penalties, defensive contribution).
A6: Top projected player | B6: =IFERROR(INDEX('PLAYER POOL'!A:A,MATCH(MAX('PLAYER POOL'!Y:Y),'PLAYER POOL'!Y:Y,0)),) | D6: 3. Fixtures third: use fixture difficulty as a multiplier, not as the entire decision.
A7: Top xP/£m | B7: =IFERROR(MAX('PLAYER POOL'!Z:Z),0) | D7: 4. Price/value fourth: xP per £m matters most when choosing among similar expected outputs.
A8: Highest minutes risk | B8: =IFERROR(MAX('PLAYER POOL'!AA:AA),0) | D8: 5. Transfers fifth: compare net gain after −4 costs and consider the next 3–6 Gameweeks.
D9: 6. Captaincy: favour high minutes + high attacking involvement + strong fixture; captaincy is a ceiling decision, not merely a value decision.
A11: Top 10 by Decision Score
A12: Rank | B12: Player | C12: Club | D12: Pos | E12: xP | F12: xP/£m | G12: Minutes risk | H12: Decision Score | I12: Captain Score
A13: 1 | B13: =IFERROR(INDEX('PLAYER POOL'!A:A,MATCH(LARGE('PLAYER POOL'!AB:AB,1),'PLAYER POOL'!AB:AB,0)),"") | C13: =IFERROR(XLOOKUP(B13,'PLAYER POOL'!A:A,'PLAYER POOL'!B:B),"") | D13: =IFERROR(XLOOKUP(B13,'PLAYER POOL'!A:A,'PLAYER POOL'!C:C),"") | E13: =IFERROR(XLOOKUP(B13,'PLAYER POOL'!A:A,'PLAYER POOL'!Y:Y),0) | F13: =IFERROR(XLOOKUP(B13,'PLAYER POOL'!A:A,'PLAYER POOL'!Z:Z),0) | G13: =IFERROR(XLOOKUP(B13,'PLAYER POOL'!A:A,'PLAYER POOL'!AA:AA),0) | H13: =IFERROR(XLOOKUP(B13,'PLAYER POOL'!A:A,'PLAYER POOL'!AB:AB),0) | I13: =IFERROR(XLOOKUP(B13,'PLAYER POOL'!A:A,'PLAYER POOL'!AC:AC),0)
A14: 2 | B14: =IFERROR(INDEX('PLAYER POOL'!A:A,MATCH(LARGE('PLAYER POOL'!AB:AB,2),'PLAYER POOL'!AB:AB,0)),"") | C14: =IFERROR(XLOOKUP(B14,'PLAYER POOL'!A:A,'PLAYER POOL'!B:B),"") | D14: =IFERROR(XLOOKUP(B14,'PLAYER POOL'!A:A,'PLAYER POOL'!C:C),"") | E14: =IFERROR(XLOOKUP(B14,'PLAYER POOL'!A:A,'PLAYER POOL'!Y:Y),0) | F14: =IFERROR(XLOOKUP(B14,'PLAYER POOL'!A:A,'PLAYER POOL'!Z:Z),0) | G14: =IFERROR(XLOOKUP(B14,'PLAYER POOL'!A:A,'PLAYER POOL'!AA:AA),0) | H14: =IFERROR(XLOOKUP(B14,'PLAYER POOL'!A:A,'PLAYER POOL'!AB:AB),0) | I14: =IFERROR(XLOOKUP(B14,'PLAYER POOL'!A:A,'PLAYER POOL'!AC:AC),0)
A15: 3 | B15: =IFERROR(INDEX('PLAYER POOL'!A:A,MATCH(LARGE('PLAYER POOL'!AB:AB,3),'PLAYER POOL'!AB:AB,0)),"") | C15: =IFERROR(XLOOKUP(B15,'PLAYER POOL'!A:A,'PLAYER POOL'!B:B),"") | D15: =IFERROR(XLOOKUP(B15,'PLAYER POOL'!A:A,'PLAYER POOL'!C:C),"") | E15: =IFERROR(XLOOKUP(B15,'PLAYER POOL'!A:A,'PLAYER POOL'!Y:Y),0) | F15: =IFERROR(XLOOKUP(B15,'PLAYER POOL'!A:A,'PLAYER POOL'!Z:Z),0) | G15: =IFERROR(XLOOKUP(B15,'PLAYER POOL'!A:A,'PLAYER POOL'!AA:AA),0) | H15: =IFERROR(XLOOKUP(B15,'PLAYER POOL'!A:A,'PLAYER POOL'!AB:AB),0) | I15: =IFERROR(XLOOKUP(B15,'PLAYER POOL'!A:A,'PLAYER POOL'!AC:AC),0)
A16: 4 | B16: =IFERROR(INDEX('PLAYER POOL'!A:A,MATCH(LARGE('PLAYER POOL'!AB:AB,4),'PLAYER POOL'!AB:AB,0)),"") | C16: =IFERROR(XLOOKUP(B16,'PLAYER POOL'!A:A,'PLAYER POOL'!B:B),"") | D16: =IFERROR(XLOOKUP(B16,'PLAYER POOL'!A:A,'PLAYER POOL'!C:C),"") | E16: =IFERROR(XLOOKUP(B16,'PLAYER POOL'!A:A,'PLAYER POOL'!Y:Y),0) | F16: =IFERROR(XLOOKUP(B16,'PLAYER POOL'!A:A,'PLAYER POOL'!Z:Z),0) | G16: =IFERROR(XLOOKUP(B16,'PLAYER POOL'!A:A,'PLAYER POOL'!AA:AA),0) | H16: =IFERROR(XLOOKUP(B16,'PLAYER POOL'!A:A,'PLAYER POOL'!AB:AB),0) | I16: =IFERROR(XLOOKUP(B16,'PLAYER POOL'!A:A,'PLAYER POOL'!AC:AC),0)
A17: 5 | B17: =IFERROR(INDEX('PLAYER POOL'!A:A,MATCH(LARGE('PLAYER POOL'!AB:AB,5),'PLAYER POOL'!AB:AB,0)),"") | C17: =IFERROR(XLOOKUP(B17,'PLAYER POOL'!A:A,'PLAYER POOL'!B:B),"") | D17: =IFERROR(XLOOKUP(B17,'PLAYER POOL'!A:A,'PLAYER POOL'!C:C),"") | E17: =IFERROR(XLOOKUP(B17,'PLAYER POOL'!A:A,'PLAYER POOL'!Y:Y),0) | F17: =IFERROR(XLOOKUP(B17,'PLAYER POOL'!A:A,'PLAYER POOL'!Z:Z),0) | G17: =IFERROR(XLOOKUP(B17,'PLAYER POOL'!A:A,'PLAYER POOL'!AA:AA),0) | H17: =IFERROR(XLOOKUP(B17,'PLAYER POOL'!A:A,'PLAYER POOL'!AB:AB),0) | I17: =IFERROR(XLOOKUP(B17,'PLAYER POOL'!A:A,'PLAYER POOL'!AC:AC),0)
A18: 6 | B18: =IFERROR(INDEX('PLAYER POOL'!A:A,MATCH(LARGE('PLAYER POOL'!AB:AB,6),'PLAYER POOL'!AB:AB,0)),"") | C18: =IFERROR(XLOOKUP(B18,'PLAYER POOL'!A:A,'PLAYER POOL'!B:B),"") | D18: =IFERROR(XLOOKUP(B18,'PLAYER POOL'!A:A,'PLAYER POOL'!C:C),"") | E18: =IFERROR(XLOOKUP(B18,'PLAYER POOL'!A:A,'PLAYER POOL'!Y:Y),0) | F18: =IFERROR(XLOOKUP(B18,'PLAYER POOL'!A:A,'PLAYER POOL'!Z:Z),0) | G18: =IFERROR(XLOOKUP(B18,'PLAYER POOL'!A:A,'PLAYER POOL'!AA:AA),0) | H18: =IFERROR(XLOOKUP(B18,'PLAYER POOL'!A:A,'PLAYER POOL'!AB:AB),0) | I18: =IFERROR(XLOOKUP(B18,'PLAYER POOL'!A:A,'PLAYER POOL'!AC:AC),0)
A19: 7 | B19: =IFERROR(INDEX('PLAYER POOL'!A:A,MATCH(LARGE('PLAYER POOL'!AB:AB,7),'PLAYER POOL'!AB:AB,0)),"") | C19: =IFERROR(XLOOKUP(B19,'PLAYER POOL'!A:A,'PLAYER POOL'!B:B),"") | D19: =IFERROR(XLOOKUP(B19,'PLAYER POOL'!A:A,'PLAYER POOL'!C:C),"") | E19: =IFERROR(XLOOKUP(B19,'PLAYER POOL'!A:A,'PLAYER POOL'!Y:Y),0) | F19: =IFERROR(XLOOKUP(B19,'PLAYER POOL'!A:A,'PLAYER POOL'!Z:Z),0) | G19: =IFERROR(XLOOKUP(B19,'PLAYER POOL'!A:A,'PLAYER POOL'!AA:AA),0) | H19: =IFERROR(XLOOKUP(B19,'PLAYER POOL'!A:A,'PLAYER POOL'!AB:AB),0) | I19: =IFERROR(XLOOKUP(B19,'PLAYER POOL'!A:A,'PLAYER POOL'!AC:AC),0)
A20: 8 | B20: =IFERROR(INDEX('PLAYER POOL'!A:A,MATCH(LARGE('PLAYER POOL'!AB:AB,8),'PLAYER POOL'!AB:AB,0)),"") | C20: =IFERROR(XLOOKUP(B20,'PLAYER POOL'!A:A,'PLAYER POOL'!B:B),"") | D20: =IFERROR(XLOOKUP(B20,'PLAYER POOL'!A:A,'PLAYER POOL'!C:C),"") | E20: =IFERROR(XLOOKUP(B20,'PLAYER POOL'!A:A,'PLAYER POOL'!Y:Y),0) | F20: =IFERROR(XLOOKUP(B20,'PLAYER POOL'!A:A,'PLAYER POOL'!Z:Z),0) | G20: =IFERROR(XLOOKUP(B20,'PLAYER POOL'!A:A,'PLAYER POOL'!AA:AA),0) | H20: =IFERROR(XLOOKUP(B20,'PLAYER POOL'!A:A,'PLAYER POOL'!AB:AB),0) | I20: =IFERROR(XLOOKUP(B20,'PLAYER POOL'!A:A,'PLAYER POOL'!AC:AC),0)
A21: 9 | B21: =IFERROR(INDEX('PLAYER POOL'!A:A,MATCH(LARGE('PLAYER POOL'!AB:AB,9),'PLAYER POOL'!AB:AB,0)),"") | C21: =IFERROR(XLOOKUP(B21,'PLAYER POOL'!A:A,'PLAYER POOL'!B:B),"") | D21: =IFERROR(XLOOKUP(B21,'PLAYER POOL'!A:A,'PLAYER POOL'!C:C),"") | E21: =IFERROR(XLOOKUP(B21,'PLAYER POOL'!A:A,'PLAYER POOL'!Y:Y),0) | F21: =IFERROR(XLOOKUP(B21,'PLAYER POOL'!A:A,'PLAYER POOL'!Z:Z),0) | G21: =IFERROR(XLOOKUP(B21,'PLAYER POOL'!A:A,'PLAYER POOL'!AA:AA),0) | H21: =IFERROR(XLOOKUP(B21,'PLAYER POOL'!A:A,'PLAYER POOL'!AB:AB),0) | I21: =IFERROR(XLOOKUP(B21,'PLAYER POOL'!A:A,'PLAYER POOL'!AC:AC),0)
A22: 10 | B22: =IFERROR(INDEX('PLAYER POOL'!A:A,MATCH(LARGE('PLAYER POOL'!AB:AB,10),'PLAYER POOL'!AB:AB,0)),"") | C22: =IFERROR(XLOOKUP(B22,'PLAYER POOL'!A:A,'PLAYER POOL'!B:B),"") | D22: =IFERROR(XLOOKUP(B22,'PLAYER POOL'!A:A,'PLAYER POOL'!C:C),"") | E22: =IFERROR(XLOOKUP(B22,'PLAYER POOL'!A:A,'PLAYER POOL'!Y:Y),0) | F22: =IFERROR(XLOOKUP(B22,'PLAYER POOL'!A:A,'PLAYER POOL'!Z:Z),0) | G22: =IFERROR(XLOOKUP(B22,'PLAYER POOL'!A:A,'PLAYER POOL'!AA:AA),0) | H22: =IFERROR(XLOOKUP(B22,'PLAYER POOL'!A:A,'PLAYER POOL'!AB:AB),0) | I22: =IFERROR(XLOOKUP(B22,'PLAYER POOL'!A:A,'PLAYER POOL'!AC:AC),0)
A25: Advanced workflow
A26: 1. WEEKLY INPUT: paste/update one row per player. Yellow cells are the only recurring inputs.
A27: 2. PLAYER MODEL: inspect projected minutes, 1GW xP and 6/8GW xP. Challenge minutes first.
A28: 3. 8GW PROJECTIONS: use for structural moves and medium-term planning.
A29: 4. TRANSFER EV: enter OUT/IN and number of transfers. A hit is automatically costed at 4 points.
A30: 5. CAPTAINCY: use the probability board, then override for late team news when justified.
A31: 6. CHIP PLANNER: score future weeks for blanks/doubles, fixture swings and squad readiness.
A32: 7. WEEKLY REVIEW: record actual vs projected points and diagnose repeated model errors.

Sheet STATISTICS & FORMULAS
A1: Statistic / Formula | B1: What it means | C1: Why it matters | D1: How to update | E1: Interpretation / caution
A2: xG | B2: Expected goals based on shot quality/position/context. | C2: More predictive of future goals than raw goals over short samples. | D2: Update from your chosen reliable data source after each GW. | E2: Use alongside minutes and role; xG is not a guarantee.
A3: xA | B3: Expected assists generated by chance creation. | C3: Captures assist potential even when teammates fail to finish. | D3: Update after each GW. | E3: Different providers model xA differently; stay consistent.
A4: xGI | B4: xG + xA. | C4: Single attacking involvement measure. | D4: Formula in Player Pool: xG/90 + xA/90. | E4: Useful for comparing attacking involvement, not defensive value.
A5: xG/90 | B5: Expected goals per 90 minutes. | C5: Separates opportunity from playing time. | D5: Formula: xG ÷ minutes × 90. | E5: Small samples can be noisy.
A6: xA/90 | B6: Expected assists per 90 minutes. | C6: Measures creative output independent of total minutes. | D6: Formula: xA ÷ minutes × 90. | E6: Role and set pieces can change quickly.
A7: Projected minutes | B7: Expected minutes next GW. | C7: Minutes are the foundation of every points projection. | D7: Estimate using starts, injury/news, manager comments, rotation and schedule congestion. | E7: Do not blindly use last-6 minutes.
A8: Start probability | B8: Chance player starts. | C8: A 20–30 minute cameo is materially different from a 90-minute starter. | D8: Enter your estimate from team news and role. | E8: Make this conservative.
A9: Fixture difficulty 1–5 | B9: Your opponent-strength rating for the next fixture. | C9: Adjusts projections for match difficulty. | D9: 1 = very favourable, 5 = very difficult. | E9: Keep the scale consistent rather than chasing tiny differences.
A10: Fixture multiplier | B10: Simple adjustment from fixture difficulty. | C10: Prevents fixtures from dominating the model while still mattering. | D10: Formula: 1 + (3 − difficulty) × 0.10. | E10: This is a transparent heuristic, not an official FPL calculation.
A11: Underlying xP | B11: Projected points before fixture adjustment. | C11: Combines appearance, attacking, defensive and form signals. | D11: Formula is in Player Pool column X. | E11: Use as a ranking input, not as a promised score.
A12: Fixture-adjusted xP | B12: Underlying xP × fixture multiplier × minutes factor. | C12: Your main one-GW projection. | D12: Formula is in Player Pool column Y. | E12: Better for decisions than raw points-per-game.
... A26: Model calibration | B26: Actual points − projected points. | C26: Shows systematic bias in the model. | D26: Record each GW. | E26: Look for repeated bias by position/club/player type rather than isolated variance.

Sheet WEEKLY CHECKLIST
A1: Timing | B1: Task | C1: What to look at | D1: Action threshold | E1: Done?
A2: Immediately after GW | B2: Review actuals | C2: Variance, minutes, role changes, injuries, penalties/set pieces | D2: Flag repeated model misses; do not chase one-off points.
A3: Monday–Tuesday | B3: Update data | C3: Minutes, starts, xG, xA, defensive contributions, price | D3: Refresh Player Pool inputs.
A4: Midweek | B4: Scan fixtures | C4: Next 6–8 GW difficulty and blanks/doubles | D4: Identify structural fixture swings, not one-match noise.
A5: Before deadline | B5: Team news | C5: Press conferences, injuries, rotation, likely XI | D5: Update projected minutes/start probability.
A6: Before deadline | B6: Compare transfers | C6: Net gain, xP/£m, future fixtures, transfer cost | D6: Usually demand a meaningful edge for a hit.
A7: Before deadline | B7: Captaincy | C7: Captain Score, projected minutes, fixture | D7: Choose the highest-confidence ceiling option; verify news.
A8: Before deadline | B8: Bench order | C8: Expected minutes and xP | D8: Bench safest likely starter first; auto-sub rules matter.
A9: After deadline | B9: Record decision | C9: Transfers, chip, captain, reasoning | D9: Make review useful: record why you acted, not just what happened.

Sheet SOURCES & NOTES
A1: Source / topic | B1: Use in workbook | C1: Notes
A2: Official FPL rules | B2: Squad structure, transfers, chips, deadlines, scoring | C2: Use the current FPL rules page as the authority if rules change during the season.
A3: Official FPL 2026/27 changes | B3: Current-season chip structure, Price Change Predictor, BPS changes | C3: 2026/27 has two sets of Wildcard, Free Hit, Triple Captain and Bench Boost.
A4: FPL glossary | B4: Terminology such as xGI and asset | C4: Definitions can change; use the current official glossary.
A5: Your chosen data provider | B5: xG, xA, minutes, shots, big chances, key passes | C5: Consistency matters more than mixing providers.
A8: Model warning | B8: The xP model here is intentionally transparent rather than a black-box recreation of an elite manager's private model. Top managers generally combine minutes/role, underlying data, fixtures, price/value, team news and opportunity cost.
A10: Current-season official rule source | B10: Premier League 2026/27 changes: https://www.premierleague.com/en/news/4679873
A11: Current-season chip source | B11: Premier League 2026/27 chip guidance: https://www.premierleague.com/en/news/4679879
A12: Official fixture source | B12: Official FPL fixtures/FDR: https://fantasy.premierleague.com/en/fixtures/fdr
A13: Recommended advanced source | B13: Understat: xG/xA and shot-quality cross-check. Use consistently; do not mix provider definitions without noting the difference.

Sheet WEEKLY INPUT
A1: Weekly Data Entry — enter only the yellow cells
A3: How this works | B3: Enter/update each player's rolling 6-GW inputs once per week. The workbook calculates per-90 rates, minutes confidence, fixture-adjusted xP and 8-GW projections automatically. Keep the same data-provider methodology throughout the season.
A5: Player | B5: Club | C5: Pos | D5: Price £m | E5: Own % | F5: Minutes L6 | G5: Starts L6 | H5: xG L6 | I5: xA L6 | J5: Goals L6 | K5: Assists L6 | L5: Shots L6 | M5: Big Chances L6 | N5: Key Passes L6 | O5: Def Contrib L6 | P5: Projected Min GW+1 | Q5: Start Prob % GW+1 | R5: Fixture Diff GW+1 | S5: Fixture Diff GW+2 | T5: Fixture Diff GW+3 | U5: Fixture Diff GW+4 | V5: Fixture Diff GW+5 | W5: Fixture Diff GW+6 | X5: Fixture Diff GW+7 | Y5: Fixture Diff GW+8 | Z5: News / role note
A207: Yellow = input. Everything else in the advanced model is calculated from these entries.

Sheet PLAYER MODEL
A1: Advanced Player Projection Engine
A2: Formula-driven decision support — not an official FPL prediction.
A3: Core idea | B3: Expected points are built from expected minutes + attacking involvement + clean-sheet/defensive contribution signals, then adjusted for fixtures and rotation. The 8-GW engine discounts further-out weeks slightly.
A5: Player | B5: Club | C5: Pos | D5: Price | E5: Own % | F5: Min L6 | G5: Start % | H5: xG/90 | I5: xA/90 | J5: xGI/90 | K5: Goals/90 | L5: Assists/90 | M5: Shots/90 | N5: BC/90 | O5: KP/90 | P5: DefCon/90 | Q5: Recent FPL Pts/90 | R5: Minutes Factor | S5: Role/News Factor | T5: Base xP GW1 | U5: Adj xP GW1 | V5: Adj xP GW2 | W5: Adj xP GW3 | X5: Adj xP GW4 | Y5: Adj xP GW5 | Z5: Adj xP GW6 | AA5: Adj xP GW7 | AB5: Adj xP GW8 | AC5: 8GW xP | AD5: 6GW xP | AE5: xP/£m | AF5: Minutes Risk | AG5: Captain Ceiling | AH5: Captain Prob | AI5: Decision Score | AJ5: Transfer Rank | AK5: Notes
A6: =IFERROR('WEEKLY INPUT'!A6,"") | B6: =IFERROR('WEEKLY INPUT'!B6,"") | C6: =IFERROR('WEEKLY INPUT'!C6,"") | D6: =IFERROR('WEEKLY INPUT'!D6,0) | E6: =IFERROR('WEEKLY INPUT'!E6,0) | F6: =IFERROR('WEEKLY INPUT'!F6,0) | G6: =IFERROR('WEEKLY INPUT'!Q6,0) | H6: =IFERROR('WEEKLY INPUT'!H6/'WEEKLY INPUT'!F6*90,0) | I6: =IFERROR('WEEKLY INPUT'!I6/'WEEKLY INPUT'!F6*90,0) | J6: =H6+I6 | K6: =IFERROR('WEEKLY INPUT'!J6/'WEEKLY INPUT'!F6*90,0) | L6: =IFERROR('WEEKLY INPUT'!K6/'WEEKLY INPUT'!F6*90,0) | M6: =IFERROR('WEEKLY INPUT'!L6/'WEEKLY INPUT'!F6*90,0) | N6: =IFERROR('WEEKLY INPUT'!M6/'WEEKLY INPUT'!F6*90,0) | O6: =IFERROR('WEEKLY INPUT'!N6/'WEEKLY INPUT'!F6*90,0) | P6: =IFERROR('WEEKLY INPUT'!O6/'WEEKLY INPUT'!F6*90,0) | Q6: =IFERROR(('WEEKLY INPUT'!J6*2+'WEEKLY INPUT'!K6*1+'WEEKLY INPUT'!O6*0.2)/'WEEKLY INPUT'!F6,0) | R6: =MAX(0.25,MIN(1.15,(F6/540)*0.5+G6*0.5)) | S6: =MAX(0.70,MIN(1.10,0.85+0.15*G6)) | T6: =IF(A6="","",2*('WEEKLY INPUT'!P6/90)+(H6*5+I6*3)*('WEEKLY INPUT'!P6/90)+(P6*0.15)*('WEEKLY INPUT'!P6/90)+Q6*0.25) | U6: =IF($A6="","",$T6*(1+($3-'WEEKLY INPUT'!R6)*0.10)*$R6*$S6*1.0) | V6: =IF($A6="","",$T6*(1+($3-'WEEKLY INPUT'!S6)*0.10)*$R6*$S6*0.975) | W6: =IF($A6="","",$T6*(1+($3-'WEEKLY INPUT'!T6)*0.10)*$R6*$S6*0.95) | X6: =IF($A6="","",$T6*(1+($3-'WEEKLY INPUT'!U6)*0.10)*$R6*$S6*0.925) | Y6: =IF($A6="","",$T6*(1+($3-'WEEKLY INPUT'!V6)*0.10)*$R6*$S6*0.9) | Z6: =IF($A6="","",$T6*(1+($3-'WEEKLY INPUT'!W6)*0.10)*$R6*$S6*0.875) | AA6: =IF($A6="","",$T6*(1+($3-'WEEKLY INPUT'!X6)*0.10)*$R6*$S6*0.85) | AB6: =IF($A6="","",$T6*(1+($3-'WEEKLY INPUT'!Y6)*0.10)*$R6*$S6*0.825) | AC6: =SUM(U6:AB6) | AD6: =SUM(U6:Z6) | AE6: =IFERROR(AD6/D6,0) | AF6: =MAX(0,1-R6) | AG6: =IFERROR((H6+I6)*R6*(1+0.10*(3-'WEEKLY INPUT'!R6)),"") | AH6: =IFERROR(AG6/SUMPRODUCT($AG$6:$AG$205),"") | AI6: =IFERROR(AD6*(1-AF6*0.5)*(1+0.15*AE6),0) | AJ6: =IF(A6="","",RANK(AI6,$AI$6:$AI$205,0)) | AK6: =IFERROR('WEEKLY INPUT'!Z6,"")
A7: =IFERROR('WEEKLY INPUT'!A7,"") | B7: =IFERROR('WEEKLY INPUT'!B7,"") | C7: =IFERROR('WEEKLY INPUT'!C7,"") | D7: =IFERROR('WEEKLY INPUT'!D7,0) | E7: =IFERROR('WEEKLY INPUT'!E7,0) | F7: =IFERROR('WEEKLY INPUT'!F7,0) | G7: =IFERROR('WEEKLY INPUT'!Q7,0) | H7: =IFERROR('WEEKLY INPUT'!H7/'WEEKLY INPUT'!F7*90,0) | I7: =IFERROR('WEEKLY INPUT'!I7/'WEEKLY INPUT'!F7*90,0) | J7: =H7+I7 | K7: =IFERROR('WEEKLY INPUT'!J7/'WEEKLY INPUT'!F7*90,0) | L7: =IFERROR('WEEKLY INPUT'!K7/'WEEKLY INPUT'!F7*90,0) | M7: =IFERROR('WEEKLY INPUT'!L7/'WEEKLY INPUT'!F7*90,0) | N7: =IFERROR('WEEKLY INPUT'!M7/'WEEKLY INPUT'!F7*90,0) | O7: =IFERROR('WEEKLY INPUT'!N7/'WEEKLY INPUT'!F7*90,0) | P7: =IFERROR('WEEKLY INPUT'!O7/'WEEKLY INPUT'!F7*90,0) | Q7: =IFERROR(('WEEKLY INPUT'!J7*2+'WEEKLY INPUT'!K7*1+'WEEKLY INPUT'!O7*0.2)/'WEEKLY INPUT'!F7,0) | R7: =MAX(0.25,MIN(1.15,(F7/540)*0.5+G7*0.5)) | S7: =MAX(0.70,MIN(1.10,0.85+0.15*G7)) | T7: =IF(A7="","",2*('WEEKLY INPUT'!P7/90)+(H7*5+I7*3)*('WEEKLY INPUT'!P7/90)+(P7*0.15)*('WEEKLY INPUT'!P7/90)+Q7*0.25) | U7: =IF($A7="","",$T7*(1+($3-'WEEKLY INPUT'!R7)*0.10)*$R7*$S7*1.0) | V7: =IF($A7="","",$T7*(1+($3-'WEEKLY INPUT'!S7)*0.10)*$R7*$S7*0.975) | W7: =IF($A7="","",$T7*(1+($3-'WEEKLY INPUT'!T7)*0.10)*$R7*$S7*0.95) | X7: =IF($A7="","",$T7*(1+($3-'WEEKLY INPUT'!U7)*0.10)*$R7*$S7*0.925) | Y7: =IF($A7="","",$T7*(1+($3-'WEEKLY INPUT'!V7)*0.10)*$R7*$S7*0.9) | Z7: =IF($A7="","",$T7*(1+($3-'WEEKLY INPUT'!W7)*0.10)*$R7*$S7*0.875) | AA7: =IF($A7="","",$T7*(1+($3-'WEEKLY INPUT'!X7)*0.10)*$R7*$S7*0.85) | AB7: =IF($A7="","",$T7*(1+($3-'WEEKLY INPUT'!Y7)*0.10)*$R7*$S7*0.825) | AC7: =SUM(U7:AB7) | AD7: =SUM(U7:Z7) | AE7: =IFERROR(AD7/D7,0) | AF7: =MAX(0,1-R7) | AG7: =IFERROR((H7+I7)*R7*(1+0.10*(3-'WEEKLY INPUT'!R7)),"") | AH7: =IFERROR(AG7/SUMPRODUCT($AG$6:$AG$205),"") | AI7: =IFERROR(AD7*(1-AF7*0.5)*(1+0.15*AE7),0) | AJ7: =IF(A7="","",RANK(AI7,$AI$6:$AI$205,0)) | AK7: =IFERROR('WEEKLY INPUT'!Z7,"")
A8: =IFERROR('WEEKLY INPUT'!A8,"") | B8: =IFERROR('WEEKLY INPUT'!B8,"") | C8: =IFERROR('WEEKLY INPUT'!C8,"") | D8: =IFERROR('WEEKLY INPUT'!D8,0) | E8: =IFERROR('WEEKLY INPUT'!E8,0) | F8: =IFERROR('WEEKLY INPUT'!F8,0) | G8: =IFERROR('WEEKLY INPUT'!Q8,0) | H8: =IFERROR('WEEKLY INPUT'!H8/'WEEKLY INPUT'!F8*90,0) | I8: =IFERROR('WEEKLY INPUT'!I8/'WEEKLY INPUT'!F8*90,0) | J8: =H8+I8 | K8: =IFERROR('WEEKLY INPUT'!J8/'WEEKLY INPUT'!F8*90,0) | L8: =IFERROR('WEEKLY INPUT'!K8/'WEEKLY INPUT'!F8*90,0) | M8: =IFERROR('WEEKLY INPUT'!L8/'WEEKLY INPUT'!F8*90,0) | N8: =IFERROR('WEEKLY INPUT'!M8/'WEEKLY INPUT'!F8*90,0) | O8: =IFERROR('WEEKLY INPUT'!N8/'WEEKLY INPUT'!F8*90,0) | P8: =IFERROR('WEEKLY INPUT'!O8/'WEEKLY INPUT'!F8*90,0) | Q8: =IFERROR(('WEEKLY INPUT'!J8*2+'WEEKLY INPUT'!K8*1+'WEEKLY INPUT'!O8*0.2)/'WEEKLY INPUT'!F8,0) | R8: =MAX(0.25,MIN(1.15,(F8/540)*0.5+G8*0.5)) | S8: =MAX(0.70,MIN(1.10,0.85+0.15*G8)) | T8: =IF(A8="","",2*('WEEKLY INPUT'!P8/90)+(H8*5+I8*3)*('WEEKLY INPUT'!P8/90)+(P8*0.15)*('WEEKLY INPUT'!P8/90)+Q8*0.25) | U8: =IF($A8="","",$T8*(1+($3-'WEEKLY INPUT'!R8)*0.10)*$R8*$S8*1.0) | V8: =IF($A8="","",$T8*(1+($3-'WEEKLY INPUT'!S8)*0.10)*$R8*$S8*0.975) | W8: =IF($A8="","",$T8*(1+($3-'WEEKLY INPUT'!T8)*0.10)*$R8*$S8*0.95) | X8: =IF($A8="","",$T8*(1+($3-'WEEKLY INPUT'!U8)*0.10)*$R8*$S8*0.925) | Y8: =IF($A8="","",$T8*(1+($3-'WEEKLY INPUT'!V8)*0.10)*$R8*$S8*0.9) | Z8: =IF($A8="","",$T8*(1+($3-'WEEKLY INPUT'!W8)*0.10)*$R8*$S8*0.875) | AA8: =IF($A8="","",$T8*(1+($3-'WEEKLY INPUT'!X8)*0.10)*$R8*$S8*0.85) | AB8: =IF($A8="","",$T8*(1+($3-'WEEKLY INPUT'!Y8)*0.10)*$R8*$S8*0.825) | AC8: =SUM(U8:AB8) | AD8: =SUM(U8:Z8) | AE8: =IFERROR(AD8/D8,0) | AF8: =MAX(0,1-R8) | AG8: =IFERROR((H8+I8)*R8*(1+0.10*(3-'WEEKLY INPUT'!R8)),"") | AH8: =IFERROR(AG8/SUMPRODUCT($AG$6:$AG$205),"") | AI8: =IFERROR(AD8*(1-AF8*0.5)*(1+0.15*AE8),0) | AJ8: =IF(A8="","",RANK(AI8,$AI$6:$AI$205,0)) | AK8: =IFERROR('WEEKLY INPUT'!Z8,"")
A9: =IFERROR('WEEKLY INPUT'!A9,"") | B9: =IFERROR('WEEKLY INPUT'!B9,"") | C9: =IFERROR('WEEKLY INPUT'!C9,"") | D9: =IFERROR('WEEKLY INPUT'!D9,0) | E9: =IFERROR('WEEKLY INPUT'!E9,0) | F9: =IFERROR('WEEKLY INPUT'!F9,0) | G9: =IFERROR('WEEKLY INPUT'!Q9,0) | H9: =IFERROR('WEEKLY INPUT'!H9/'WEEKLY INPUT'!F9*90,0) | I9: =IFERROR('WEEKLY INPUT'!I9/'WEEKLY INPUT'!F9*90,0) | J9: =H9+I9 | K9: =IFERROR('WEEKLY INPUT'!J9/'WEEKLY INPUT'!F9*90,0) | L9: =IFERROR('WEEKLY INPUT'!K9/'WEEKLY INPUT'!F9*90,0) | M9: =IFERROR('WEEKLY INPUT'!L9/'WEEKLY INPUT'!F9*90,0) | N9: =IFERROR('WEEKLY INPUT'!M9/'WEEKLY INPUT'!F9*90,0) | O9: =IFERROR('WEEKLY INPUT'!N9/'WEEKLY INPUT'!F9*90,0) | P9: =IFERROR('WEEKLY INPUT'!O9/'WEEKLY INPUT'!F9*90,0) | Q9: =IFERROR(('WEEKLY INPUT'!J9*2+'WEEKLY INPUT'!K9*1+'WEEKLY INPUT'!O9*0.2)/'WEEKLY INPUT'!F9,0) | R9: =MAX(0.25,MIN(1.15,(F9/540)*0.5+G9*0.5)) | S9: =MAX(0.70,MIN(1.10,0.85+0.15*G9)) | T9: =IF(A9="","",2*('WEEKLY INPUT'!P9/90)+(H9*5+I9*3)*('WEEKLY INPUT'!P9/90)+(P9*0.15)*('WEEKLY INPUT'!P9/90)+Q9*0.25) | U9: =IF($A9="","",$T9*(1+($3-'WEEKLY INPUT'!R9)*0.10)*$R9*$S9*1.0) | V9: =IF($A9="","",$T9*(1+($3-'WEEKLY INPUT'!S9)*0.10)*$R9*$S9*0.975) | W9: =IF($A9="","",$T9*(1+($3-'WEEKLY INPUT'!T9)*0.10)*$R9*$S9*0.95) | X9: =IF($A9="","",$T9*(1+($3-'WEEKLY INPUT'!U9)*0.10)*$R9*$S9*0.925) | Y9: =IF($A9="","",$T9*(1+($3-'WEEKLY INPUT'!V9)*0.10)*$R9*$S9*0.9) | Z9: =IF($A9="","",$T9*(1+($3-'WEEKLY INPUT'!W9)*0.10)*$R9*$S9*0.875) | AA9: =IF($A9="","",$T9*(1+($3-'WEEKLY INPUT'!X9)*0.10)*$R9*$S9*0.85) | AB9: =IF($A9="","",$T9*(1+($3-'WEEKLY INPUT'!Y9)*0.10)*$R9*$S9*0.825) | AC9: =SUM(U9:AB9) | AD9: =SUM(U9:Z9) | AE9: =IFERROR(AD9/D9,0) | AF9: =MAX(0,1-R9) | AG9: =IFERROR((H9+I9)*R9*(1+0.10*(3-'WEEKLY INPUT'!R9)),"") | AH9: =IFERROR(AG9/SUMPRODUCT($AG$6:$AG$205),"") | AI9: =IFERROR(AD9*(1-AF9*0.5)*(1+0.15*AE9),0) | AJ9: =IF(A9="","",RANK(AI9,$AI$6:$AI$205,0)) | AK9: =IFERROR('WEEKLY INPUT'!Z9,"")
A10: =IFERROR('WEEKLY INPUT'!A10,"") | B10: =IFERROR('WEEKLY INPUT'!B10,"") | C10: =IFERROR('WEEKLY INPUT'!C10,"") | D10: =IFERROR('WEEKLY INPUT'!D10,0) | E10: =IFERROR('WEEKLY INPUT'!E10,0) | F10: =IFERROR('WEEKLY INPUT'!F10,0) | G10: =IFERROR('WEEKLY INPUT'!Q10,0) | H10: =IFERROR('WEEKLY INPUT'!H10/'WEEKLY INPUT'!F10*90,0) | I10: =IFERROR('WEEKLY INPUT'!I10/'WEEKLY INPUT'!F10*90,0) | J10: =H10+I10 | K10: =IFERROR('WEEKLY INPUT'!J10/'WEEKLY INPUT'!F10*90,0) | L10: =IFERROR('WEEKLY INPUT'!K10/'WEEKLY INPUT'!F10*90,0) | M10: =IFERROR('WEEKLY INPUT'!L10/'WEEKLY INPUT'!F10*90,0) | N10: =IFERROR('WEEKLY INPUT'!M10/'WEEKLY INPUT'!F10*90,0) | O10: =IFERROR('WEEKLY INPUT'!N10/'WEEKLY INPUT'!F10*90,0) | P10: =IFERROR('WEEKLY INPUT'!O10/'WEEKLY INPUT'!F10*90,0) | Q10: =IFERROR(('WEEKLY INPUT'!J10*2+'WEEKLY INPUT'!K10*1+'WEEKLY INPUT'!O10*0.2)/'WEEKLY INPUT'!F10,0) | R10: =MAX(0.25,MIN(1.15,(F10/540)*0.5+G10*0.5)) | S10: =MAX(0.70,MIN(1.10,0.85+0.15*G10)) | T10: =IF(A10="","",2*('WEEKLY INPUT'!P10/90)+(H10*5+I10*3)*('WEEKLY INPUT'!P10/90)+(P10*0.15)*('WEEKLY INPUT'!P10/90)+Q10*0.25) | U10: =IF($A10="","",$T10*(1+($3-'WEEKLY INPUT'!R10)*0.10)*$R10*$S10*1.0) | V10: =IF($A10="","",$T10*(1+($3-'WEEKLY INPUT'!S10)*0.10)*$R10*$S10*0.975) | W10: =IF($A10="","",$T10*(1+($3-'WEEKLY INPUT'!T10)*0.10)*$R10*$S10*0.95) | X10: =IF($A10="","",$T10*(1+($3-'WEEKLY INPUT'!U10)*0.10)*$R10*$S10*0.925) | Y10: =IF($A10="","",$T10*(1+($3-'WEEKLY INPUT'!V10)*0.10)*$R10*$S10*0.9) | Z10: =IF($A10="","",$T10*(1+($3-'WEEKLY INPUT'!W10)*0.10)*$R10*$S10*0.875) | AA10: =IF($A10="","",$T10*(1+($3-'WEEKLY INPUT'!X10)*0.10)*$R10*$S10*0.85) | AB10: =IF($A10="","",$T10*(1+($3-'WEEKLY INPUT'!Y10)*0.10)*$R10*$S10*0.825) | AC10: =SUM(U10:AB10) | AD10: =SUM(U10:Z10) | AE10: =IFERROR(AD10/D10,0) | AF10: =MAX(0,1-R10) | AG10: =IFERROR((H10+I10)*R10*(1+0.10*(3-'WEEKLY INPUT'!R10)),"") | AH10: =IFERROR(AG10/SUMPRODUCT($AG$6:$AG$205),"") | AI10: =IFERROR(AD10*(1-AF10*0.5)*(1+0.15*AE10),0) | AJ10: =IF(A10="","",RANK(AI10,$AI$6:$AI$205,0)) | AK10: =IFERROR('WEEKLY INPUT'!Z10,"")
A11: =IFERROR('WEEKLY INPUT'!A11,"") | B11: =IFERROR('WEEKLY INPUT'!B11,"") | C11: =IFERROR('WEEKLY INPUT'!C11,"") | D11: =IFERROR('WEEKLY INPUT'!D11,0) | E11: =IFERROR('WEEKLY INPUT'!E11,0) | F11: =IFERROR('WEEKLY INPUT'!F11,0) | G11: =IFERROR('WEEKLY INPUT'!Q11,0) | H11: =IFERROR('WEEKLY INPUT'!H11/'WEEKLY INPUT'!F11*90,0) | I11: =IFERROR('WEEKLY INPUT'!I11/'WEEKLY INPUT'!F11*90,0) | J11: =H11+I11 | K11: =IFERROR('WEEKLY INPUT'!J11/'WEEKLY INPUT'!F11*90,0) | L11: =IFERROR('WEEKLY INPUT'!K11/'WEEKLY INPUT'!F11*90,0) | M11: =IFERROR('WEEKLY INPUT'!L11/'WEEKLY INPUT'!F11*90,0) | N11: =IFERROR('WEEKLY INPUT'!M11/'WEEKLY INPUT'!F11*90,0) | O11: =IFERROR('WEEKLY INPUT'!N11/'WEEKLY INPUT'!F11*90,0) | P11: =IFERROR('WEEKLY INPUT'!O11/'WEEKLY INPUT'!F11*90,0) | Q11: =IFERROR(('WEEKLY INPUT'!J11*2+'WEEKLY INPUT'!K11*1+'WEEKLY INPUT'!O11*0.2)/'WEEKLY INPUT'!F11,0) | R11: =MAX(0.25,MIN(1.15,(F11/540)*0.5+G11*0.5)) | S11: =MAX(0.70,MIN(1.10,0.85+0.15*G11)) | T11: =IF(A11="","",2*('WEEKLY INPUT'!P11/90)+(H11*5+I11*3)*('WEEKLY INPUT'!P11/90)+(P11*0.15)*('WEEKLY INPUT'!P11/90)+Q11*0.25) | U11: =IF($A11="","",$T11*(1+($3-'WEEKLY INPUT'!R11)*0.10)*$R11*$S11*1.0) | V11: =IF($A11="","",$T11*(1+($3-'WEEKLY INPUT'!S11)*0.10)*$R11*$S11*0.975) | W11: =IF($A11="","",$T11*(1+($3-'WEEKLY INPUT'!T11)*0.10)*$R11*$S11*0.95) | X11: =IF($A11="","",$T11*(1+($3-'WEEKLY INPUT'!U11)*0.10)*$R11*$S11*0.925) | Y11: =IF($A11="","",$T11*(1+($3-'WEEKLY INPUT'!V11)*0.10)*$R11*$S11*0.9) | Z11: =IF($A11="","",$T11*(1+($3-'WEEKLY INPUT'!W11)*0.10)*$R11*$S11*0.875) | AA11: =IF($A11="","",$T11*(1+($3-'WEEKLY INPUT'!X11)*0.10)*$R11*$S11*0.85) | AB11: =IF($A11="","",$T11*(1+($3-'WEEKLY INPUT'!Y11)*0.10)*$R11*$S11*0.825) | AC11: =SUM(U11:AB11) | AD11: =SUM(U11:Z11) | AE11: =IFERROR(AD11/D11,0) | AF11: =MAX(0,1-R11) | AG11: =IFERROR((H11+I11)*R11*(1+0.10*(3-'WEEKLY INPUT'!R11)),"") | AH11: =IFERROR(AG11/SUMPRODUCT($AG$6:$AG$205),"") | AI11: =IFERROR(AD11*(1-AF11*0.5)*(1+0.15*AE11),0) | AJ11: =IF(A11="","",RANK(AI11,$AI$6:$AI$205,0)) | AK11: =IFERROR('WEEKLY INPUT'!Z11,"")
A12: =IFERROR('WEEKLY INPUT'!A12,"") | B12: =IFERROR('WEEKLY INPUT'!B12,"") | C12: =IFERROR('WEEKLY INPUT'!C12,"") | D12: =IFERROR('WEEKLY INPUT'!D12,0) | E12: =IFERROR('WEEKLY INPUT'!E12,0) | F12: =IFERROR('WEEKLY INPUT'!F12,0) | G12: =IFERROR('WEEKLY INPUT'!Q12,0) | H12: =IFERROR('WEEKLY INPUT'!H12/'WEEKLY INPUT'!F12*90,0) | I12: =IFERROR('WEEKLY INPUT'!I12/'WEEKLY INPUT'!F12*90,0) | J12: =H12+I12 | K12: =IFERROR('WEEKLY INPUT'!J12/'WEEKLY INPUT'!F12*90,0) | L12: =IFERROR('WEEKLY INPUT'!K12/'WEEKLY INPUT'!F12*90,0) | M12: =IFERROR('WEEKLY INPUT'!L12/'WEEKLY INPUT'!F12*90,0) | N12: =IFERROR('WEEKLY INPUT'!M12/'WEEKLY INPUT'!F12*90,0) | O12: =IFERROR('WEEKLY INPUT'!N12/'WEEKLY INPUT'!F12*90,0) | P12: =IFERROR('WEEKLY INPUT'!O12/'WEEKLY INPUT'!F12*90,0) | Q12: =IFERROR(('WEEKLY INPUT'!J12*2+'WEEKLY INPUT'!K12*1+'WEEKLY INPUT'!O12*0.2)/'WEEKLY INPUT'!F12,0) | R12: =MAX(0.25,MIN(1.15,(F12/540)*0.5+G12*0.5)) | S12: =MAX(0.70,MIN(1.10,0.85+0.15*G12)) | T12: =IF(A12="","",2*('WEEKLY INPUT'!P12/90)+(H12*5+I12*3)*('WEEKLY INPUT'!P12/90)+(P12*0.15)*('WEEKLY INPUT'!P12/90)+Q12*0.25) | U12: =IF($A12="","",$T12*(1+($3-'WEEKLY INPUT'!R12)*0.10)*$R12*$S12*1.0) | V12: =IF($A12="","",$T12*(1+($3-'WEEKLY INPUT'!S12)*0.10)*$R12*$S12*0.975) | W12: =IF($A12="","",$T12*(1+($3-'WEEKLY INPUT'!T12)*0.10)*$R12*$S12*0.95) | X12: =IF($A12="","",$T12*(1+($3-'WEEKLY INPUT'!U12)*0.10)*$R12*$S12*0.925) | Y12: =IF($A12="","",$T12*(1+($3-'WEEKLY INPUT'!V12)*0.10)*$R12*$S12*0.9) | Z12: =IF($A12="","",$T12*(1+($3-'WEEKLY INPUT'!W12)*0.10)*$R12*$S12*0.875) | AA12: =IF($A12="","",$T12*(1+($3-'WEEKLY INPUT'!X12)*0.10)*$R12*$S12*0.85) | AB12: =IF($A12="","",$T12*(1+($3-'WEEKLY INPUT'!Y12)*0.10)*$R12*$S12*0.825) | AC12: =SUM(U12:AB12) | AD12: =SUM(U12:Z12) | AE12: =IFERROR(AD12/D12,0) | AF12: =MAX(0,1-R12) | AG12: =IFERROR((H12+I12)*R12*(1+0.10*(3-'WEEKLY INPUT'!R12)),"") | AH12: =IFERROR(AG12/SUMPRODUCT($AG$6:$AG$205),"") | AI12: =IFERROR(AD12*(1-AF12*0.5)*(1+0.15*AE12),0) | AJ12: =IF(A12="","",RANK(AI12,$AI$6:$AI$205,0)) | AK12: =IFERROR('WEEKLY INPUT'!Z12,"")
A13: =IFERROR('WEEKLY INPUT'!A13,"") | B13: =IFERROR('WEEKLY INPUT'!B13,"") | C13: =IFERROR('WEEKLY INPUT'!C13,"") | D13: =IFERROR('WEEKLY INPUT'!D13,0) | E13: =IFERROR('WEEKLY INPUT'!E13,0) | F13: =IFERROR('WEEKLY INPUT'!F13,0) | G13: =IFERROR('WEEKLY INPUT'!Q13,0) | H13: =IFERROR('WEEKLY INPUT'!H13/'WEEKLY INPUT'!F13*90,0) | I13: =IFERROR('WEEKLY INPUT'!I13/'WEEKLY INPUT'!F13*90,0) | J13: =H13+I13 | K13: =IFERROR('WEEKLY INPUT'!J13/'WEEKLY INPUT'!F13*90,0) | L13: =IFERROR('WEEKLY INPUT'!K13/'WEEKLY INPUT'!F13*90,0) | M13: =IFERROR('WEEKLY INPUT'!L13/'WEEKLY INPUT'!F13*90,0) | N13: =IFERROR('WEEKLY INPUT'!M13/'WEEKLY INPUT'!F13*90,0) | O13: =IFERROR('WEEKLY INPUT'!N13/'WEEKLY INPUT'!F13*90,0) | P13: =IFERROR('WEEKLY INPUT'!O13/'WEEKLY INPUT'!F13*90,0) | Q13: =IFERROR(('WEEKLY INPUT'!J13*2+'WEEKLY INPUT'!K13*1+'WEEKLY INPUT'!O13*0.2)/'WEEKLY INPUT'!F13,0) | R13: =MAX(0.25,MIN(1.15,(F13/540)*0.5+G13*0.5)) | S13: =MAX(0.70,MIN(1.10,0.85+0.15*G13)) | T13: =IF(A13="","",2*('WEEKLY INPUT'!P13/90)+(H13*5+I13*3)*('WEEKLY INPUT'!P13/90)+(P13*0.15)*('WEEKLY INPUT'!P13/90)+Q13*0.25) | U13: =IF($A13="","",$T13*(1+($3-'WEEKLY INPUT'!R13)*0.10)*$R13*$S13*1.0) | V13: =IF($A13="","",$T13*(1+($3-'WEEKLY INPUT'!S13)*0.10)*$R13*$S13*0.975) | W13: =IF($A13="","",$T13*(1+($3-'WEEKLY INPUT'!T13)*0.10)*$R13*$S13*0.95) | X13: =IF($A13="","",$T13*(1+($3-'WEEKLY INPUT'!U13)*0.10)*$R13*$S13*0.925) | Y13: =IF($A13="","",$T13*(1+($3-'WEEKLY INPUT'!V13)*0.10)*$R13*$S13*0.9) | Z13: =IF($A13="","",$T13*(1+($3-'WEEKLY INPUT'!W13)*0.10)*$R13*$S13*0.875) | AA13: =IF($A13="","",$T13*(1+($3-'WEEKLY INPUT'!X13)*0.10)*$R13*$S13*0.85) | AB13: =IF($A13="","",$T13*(1+($3-'WEEKLY INPUT'!Y13)*0.10)*$R13*$S13*0.825) | AC13: =SUM(U13:AB13) | AD13: =SUM(U13:Z13) | AE13: =IFERROR(AD13/D13,0) | AF13: =MAX(0,1-R13) | AG13: =IFERROR((H13+I13)*R13*(1+0.10*(3-'WEEKLY INPUT'!R13)),"") | AH13: =IFERROR(AG13/SUMPRODUCT($AG$6:$AG$205),"") | AI13: =IFERROR(AD13*(1-AF13*0.5)*(1+0.15*AE13),0) | AJ13: =IF(A13="","",RANK(AI13,$AI$6:$AI$205,0)) | AK13: =IFERROR('WEEKLY INPUT'!Z13,"")
A14: =IFERROR('WEEKLY INPUT'!A14,"") | B14: =IFERROR('WEEKLY INPUT'!B14,"") | C14: =IFERROR('WEEKLY INPUT'!C14,"") | D14: =IFERROR('WEEKLY INPUT'!D14,0) | E14: =IFERROR('WEEKLY INPUT'!E14,0) | F14: =IFERROR('WEEKLY INPUT'!F14,0) | G14: =IFERROR('WEEKLY INPUT'!Q14,0) | H14: =IFERROR('WEEKLY INPUT'!H14/'WEEKLY INPUT'!F14*90,0) | I14: =IFERROR('WEEKLY INPUT'!I14/'WEEKLY INPUT'!F14*90,0) | J14: =H14+I14 | K14: =IFERROR('WEEKLY INPUT'!J14/'WEEKLY INPUT'!F14*90,0) | L14: =IFERROR('WEEKLY INPUT'!K14/'WEEKLY INPUT'!F14*90,0) | M14: =IFERROR('WEEKLY INPUT'!L14/'WEEKLY INPUT'!F14*90,0) | N14: =IFERROR('WEEKLY INPUT'!M14/'WEEKLY INPUT'!F14*90,0) | O14: =IFERROR('WEEKLY INPUT'!N14/'WEEKLY INPUT'!F14*90,0) | P14: =IFERROR('WEEKLY INPUT'!O14/'WEEKLY INPUT'!F14*90,0) | Q14: =IFERROR(('WEEKLY INPUT'!J14*2+'WEEKLY INPUT'!K14*1+'WEEKLY INPUT'!O14*0.2)/'WEEKLY INPUT'!F14,0) | R14: =MAX(0.25,MIN(1.15,(F14/540)*0.5+G14*0.5)) | S14: =MAX(0.70,MIN(1.10,0.85+0.15*G14)) | T14: =IF(A14="","",2*('WEEKLY INPUT'!P14/90)+(H14*5+I14*3)*('WEEKLY INPUT'!P14/90)+(P14*0.15)*('WEEKLY INPUT'!P14/90)+Q14*0.25) | U14: =IF($A14="","",$T14*(1+($3-'WEEKLY INPUT'!R14)*0.10)*$R14*$S14*1.0) | V14: =IF($A14="","",$T14*(1+($3-'WEEKLY INPUT'!S14)*0.10)*$R14*$S14*0.975) | W14: =IF($A14="","",$T14*(1+($3-'WEEKLY INPUT'!T14)*0.10)*$R14*$S14*0.95) | X14: =IF($A14="","",$T14*(1+($3-'WEEKLY INPUT'!U14)*0.10)*$R14*$S14*0.925) | Y14: =IF($A14="","",$T14*(1+($3-'WEEKLY INPUT'!V14)*0.10)*$R14*$S14*0.9) | Z14: =IF($A14="","",$T14*(1+($3-'WEEKLY INPUT'!W14)*0.10)*$R14*$S14*0.875) | AA14: =IF($A14="","",$T14*(1+($3-'WEEKLY INPUT'!X14)*0.10)*$R14*$S14*0.85) | AB14: =IF($A14="","",$T14*(1+($3-'WEEKLY INPUT'!Y14)*0.10)*$R14*$S14*0.825) | AC14: =SUM(U14:AB14) | AD14: =SUM(U14:Z14) | AE14: =IFERROR(AD14/D14,0) | AF14: =MAX(0,1-R14) | AG14: =IFERROR((H14+I14)*R14*(1+0.10*(3-'WEEKLY INPUT'!R14)),"") | AH14: =IFERROR(AG14/SUMPRODUCT($AG$6:$AG$205),"") | AI14: =IFERROR(AD14*(1-AF14*0.5)*(1+0.15*AE14),0) | AJ14: =IF(A14="","",RANK(AI14,$AI$6:$AI$205,0)) | AK14: =IFERROR('WEEKLY INPUT'!Z14,"")
A15: =IFERROR('WEEKLY INPUT'!A15,"") | B15: =IFERROR('WEEKLY INPUT'!B15,"") | C15: =IFERROR('WEEKLY INPUT'!C15,"") | D15: =IFERROR('WEEKLY INPUT'!D15,0) | E15: =IFERROR('WEEKLY INPUT'!E15,0) | F15: =IFERROR('WEEKLY INPUT'!F15,0) | G15: =IFERROR('WEEKLY INPUT'!Q15,0) | H15: =IFERROR('WEEKLY INPUT'!H15/'WEEKLY INPUT'!F15*90,0) | I15: =IFERROR('WEEKLY INPUT'!I15/'WEEKLY INPUT'!F15*90,0) | J15: =H15+I15 | K15: =IFERROR('WEEKLY INPUT'!J15/'WEEKLY INPUT'!F15*90,0) | L15: =IFERROR('WEEKLY INPUT'!K15/'WEEKLY INPUT'!F15*90,0) | M15: =IFERROR('WEEKLY INPUT'!L15/'WEEKLY INPUT'!F15*90,0) | N15: =IFERROR('WEEKLY INPUT'!M15/'WEEKLY INPUT'!F15*90,0) | O15: =IFERROR('WEEKLY INPUT'!N15/'WEEKLY INPUT'!F15*90,0) | P15: =IFERROR('WEEKLY INPUT'!O15/'WEEKLY INPUT'!F15*90,0) | Q15: =IFERROR(('WEEKLY INPUT'!J15*2+'WEEKLY INPUT'!K15*1+'WEEKLY INPUT'!O15*0.2)/'WEEKLY INPUT'!F15,0) | R15: =MAX(0.25,MIN(1.15,(F15/540)*0.5+G15*0.5)) | S15: =MAX(0.70,MIN(1.10,0.85+0.15*G15)) | T15: =IF(A15="","",2*('WEEKLY INPUT'!P15/90)+(H15*5+I15*3)*('WEEKLY INPUT'!P15/90)+(P15*0.15)*('WEEKLY INPUT'!P15/90)+Q15*0.25) | U15: =IF($A15="","",$T15*(1+($3-'WEEKLY INPUT'!R15)*0.10)*$R15*$S15*1.0) | V15: =IF($A15="","",$T15*(1+($3-'WEEKLY INPUT'!S15)*0.10)*$R15*$S15*0.975) | W15: =IF($A15="","",$T15*(1+($3-'WEEKLY INPUT'!T15)*0.10)*$R15*$S15*0.95) | X15: =IF($A15="","",$T15*(1+($3-'WEEKLY INPUT'!U15)*0.10)*$R15*$S15*0.925) | Y15: =IF($A15="","",$T15*(1+($3-'WEEKLY INPUT'!V15)*0.10)*$R15*$S15*0.9) | Z15: =IF($A15="","",$T15*(1+($3-'WEEKLY INPUT'!W15)*0.10)*$R15*$S15*0.875) | AA15: =IF($A15="","",$T15*(1+($3-'WEEKLY INPUT'!X15)*0.10)*$R15*$S15*0.85) | AB15: =IF($A15="","",$T15*(1+($3-'WEEKLY INPUT'!Y15)*0.10)*$R15*$S15*0.825) | AC15: =SUM(U15:AB15) | AD15: =SUM(U15:Z15) | AE15: =IFERROR(AD15/D15,0) | AF15: =MAX(0,1-R15) | AG15: =IFERROR((H15+I15)*R15*(1+0.10*(3-'WEEKLY INPUT'!R15)),"") | AH15: =IFERROR(AG15/SUMPRODUCT($AG$6:$AG$205),"") | AI15: =IFERROR(AD15*(1-AF15*0.5)*(1+0.15*AE15),0) | AJ15: =IF(A15="","",RANK(AI15,$AI$6:$AI$205,0)) | AK15: =IFERROR('WEEKLY INPUT'!Z15,"")
A16: =IFERROR('WEEKLY INPUT'!A16,"") | B16: =IFERROR('WEEKLY INPUT'!B16,"") | C16: =IFERROR('WEEKLY INPUT'!C16,"") | D16: =IFERROR('WEEKLY INPUT'!D16,0) | E16: =IFERROR('WEEKLY INPUT'!E16,0) | F16: =IFERROR('WEEKLY INPUT'!F16,0) | G16: =IFERROR('WEEKLY INPUT'!Q16,0) | H16: =IFERROR('WEEKLY INPUT'!H16/'WEEKLY INPUT'!F16*90,0) | I16: =IFERROR('WEEKLY INPUT'!I16/'WEEKLY INPUT'!F16*90,0) | J16: =H16+I16 | K16: =IFERROR('WEEKLY INPUT'!J16/'WEEKLY INPUT'!F16*90,0) | L16: =IFERROR('WEEKLY INPUT'!K16/'WEEKLY INPUT'!F16*90,0) | M16: =IFERROR('WEEKLY INPUT'!L16/'WEEKLY INPUT'!F16*90,0) | N16: =IFERROR('WEEKLY INPUT'!M16/'WEEKLY INPUT'!F16*90,0) | O16: =IFERROR('WEEKLY INPUT'!N16/'WEEKLY INPUT'!F16*90,0) | P16: =IFERROR('WEEKLY INPUT'!O16/'WEEKLY INPUT'!F16*90,0) | Q16: =IFERROR(('WEEKLY INPUT'!J16*2+'WEEKLY INPUT'!K16*1+'WEEKLY INPUT'!O16*0.2)/'WEEKLY INPUT'!F16,0) | R16: =MAX(0.25,MIN(1.15,(F16/540)*0.5+G16*0.5)) | S16: =MAX(0.70,MIN(1.10,0.85+0.15*G16)) | T16: =IF(A16="","",2*('WEEKLY INPUT'!P16/90)+(H16*5+I16*3)*('WEEKLY INPUT'!P16/90)+(P16*0.15)*('WEEKLY INPUT'!P16/90)+Q16*0.25) | U16: =IF($A16="","",$T16*(1+($3-'WEEKLY INPUT'!R16)*0.10)*$R16*$S16*1.0) | V16: =IF($A16="","",$T16*(1+($3-'WEEKLY INPUT'!S16)*0.10)*$R16*$S16*0.975) | W16: =IF($A16="","",$T16*(1+($3-'WEEKLY INPUT'!T16)*0.10)*$R16*$S16*0.95) | X16: =IF($A16="","",$T16*(1+($3-'WEEKLY INPUT'!U16)*0.10)*$R16*$S16*0.925) | Y16: =IF($A16="","",$T16*(1+($3-'WEEKLY INPUT'!V16)*0.10)*$R16*$S16*0.9) | Z16: =IF($A16="","",$T16*(1+($3-'WEEKLY INPUT'!W16)*0.10)*$R16*$S16*0.875) | AA16: =IF($A16="","",$T16*(1+($3-'WEEKLY INPUT'!X16)*0.10)*$R16*$S16*0.85) | AB16: =IF($A16="","",$T16*(1+($3-'WEEKLY INPUT'!Y16)*0.10)*$R16*$S16*0.825) | AC16: =SUM(U16:AB16) | AD16: =SUM(U16:Z16) | AE16: =IFERROR(AD16/D16,0) | AF16: =MAX(0,1-R16) | AG16: =IFERROR((H16+I16)*R16*(1+0.10*(3-'WEEKLY INPUT'!R16)),"") | AH16: =IFERROR(AG16/SUMPRODUCT($AG$6:$AG$205),"") | AI16: =IFERROR(AD16*(1-AF16*0.5)*(1+0.15*AE16),0) | AJ16: =IF(A16="","",RANK(AI16,$AI$6:$AI$205,0)) | AK16: =IFERROR('WEEKLY INPUT'!Z16,"")
A17: =IFERROR('WEEKLY INPUT'!A17,"") | B17: =IFERROR('WEEKLY INPUT'!B17,"") | C17: =IFERROR('WEEKLY INPUT'!C17,"") | D17: =IFERROR('WEEKLY INPUT'!D17,0) | E17: =IFERROR('WEEKLY INPUT'!E17,0) | F17: =IFERROR('WEEKLY INPUT'!F17,0) | G17: =IFERROR('WEEKLY INPUT'!Q17,0) | H17: =IFERROR('WEEKLY INPUT'!H17/'WEEKLY INPUT'!F17*90,0) | I17: =IFERROR('WEEKLY INPUT'!I17/'WEEKLY INPUT'!F17*90,0) | J17: =H17+I17 | K17: =IFERROR('WEEKLY INPUT'!J17/'WEEKLY INPUT'!F17*90,0) | L17: =IFERROR('WEEKLY INPUT'!K17/'WEEKLY INPUT'!F17*90,0) | M17: =IFERROR('WEEKLY INPUT'!L17/'WEEKLY INPUT'!F17*90,0) | N17: =IFERROR('WEEKLY INPUT'!M17/'WEEKLY INPUT'!F17*90,0) | O17: =IFERROR('WEEKLY INPUT'!N17/'WEEKLY INPUT'!F17*90,0) | P17: =IFERROR('WEEKLY INPUT'!O17/'WEEKLY INPUT'!F17*90,0) | Q17: =IFERROR(('WEEKLY INPUT'!J17*2+'WEEKLY INPUT'!K17*1+'WEEKLY INPUT'!O17*0.2)/'WEEKLY INPUT'!F17,0) | R17: =MAX(0.25,MIN(1.15,(F17/540)*0.5+G17*0.5)) | S17: =MAX(0.70,MIN(1.10,0.85+0.15*G17)) | T17: =IF(A17="","",2*('WEEKLY INPUT'!P17/90)+(H17*5+I17*3)*('WEEKLY INPUT'!P17/90)+(P17*0.15)*('WEEKLY INPUT'!P17/90)+Q17*0.25) | U17: =IF($A17="","",$T17*(1+($3-'WEEKLY INPUT'!R17)*0.10)*$R17*$S17*1.0) | V17: =IF($A17="","",$T17*(1+($3-'WEEKLY INPUT'!S17)*0.10)*$R17*$S17*0.975) | W17: =IF($A17="","",$T17*(1+($3-'WEEKLY INPUT'!T17)*0.10)*$R17*$S17*0.95) | X17: =IF($A17="","",$T17*(1+($3-'WEEKLY INPUT'!U17)*0.10)*$R17*$S17*0.925) | Y17: =IF($A17="","",$T17*(1+($3-'WEEKLY INPUT'!V17)*0.10)*$R17*$S17*0.9) | Z17: =IF($A17="","",$T17*(1+($3-'WEEKLY INPUT'!W17)*0.10)*$R17*$S17*0.875) | AA17: =IF($A17="","",$T17*(1+($3-'WEEKLY INPUT'!X17)*0.10)*$R17*$S17*0.85) | AB17: =IF($A17="","",$T17*(1+($3-'WEEKLY INPUT'!Y17)*0.10)*$R17*$S17*0.825) | AC17: =SUM(U17:AB17) | AD17: =SUM(U17:Z17) | AE17: =IFERROR(AD17/D17,0) | AF17: =MAX(0,1-R17) | AG17: =IFERROR((H17+I17)*R17*(1+0.10*(3-'WEEKLY INPUT'!R17)),"") | AH17: =IFERROR(AG17/SUMPRODUCT($AG$6:$AG$205),"") | AI17: =IFERROR(AD17*(1-AF17*0.5)*(1+0.15*AE17),0) | AJ17: =IF(A17="","",RANK(AI17,$AI$6:$AI$205,0)) | AK17: =IFERROR('WEEKLY INPUT'!Z17,"")
... A205: =IFERROR('WEEKLY INPUT'!A205,"") | B205: =IFERROR('WEEKLY INPUT'!B205,"") | C205: =IFERROR('WEEKLY INPUT'!C205,"") | D205: =IFERROR('WEEKLY INPUT'!D205,0) | E205: =IFERROR('WEEKLY INPUT'!E205,0) | F205: =IFERROR('WEEKLY INPUT'!F205,0) | G205: =IFERROR('WEEKLY INPUT'!Q205,0) | H205: =IFERROR('WEEKLY INPUT'!H205/'WEEKLY INPUT'!F205*90,0) | I205: =IFERROR('WEEKLY INPUT'!I205/'WEEKLY INPUT'!F205*90,0) | J205: =H205+I205 | K205: =IFERROR('WEEKLY INPUT'!J205/'WEEKLY INPUT'!F205*90,0) | L205: =IFERROR('WEEKLY INPUT'!K205/'WEEKLY INPUT'!F205*90,0) | M205: =IFERROR('WEEKLY INPUT'!L205/'WEEKLY INPUT'!F205*90,0) | N205: =IFERROR('WEEKLY INPUT'!M205/'WEEKLY INPUT'!F205*90,0) | O205: =IFERROR('WEEKLY INPUT'!N205/'WEEKLY INPUT'!F205*90,0) | P205: =IFERROR('WEEKLY INPUT'!O205/'WEEKLY INPUT'!F205*90,0) | Q205: =IFERROR(('WEEKLY INPUT'!J205*2+'WEEKLY INPUT'!K205*1+'WEEKLY INPUT'!O205*0.2)/'WEEKLY INPUT'!F205,0) | R205: =MAX(0.25,MIN(1.15,(F205/540)*0.5+G205*0.5)) | S205: =MAX(0.70,MIN(1.10,0.85+0.15*G205)) | T205: =IF(A205="","",2*('WEEKLY INPUT'!P205/90)+(H205*5+I205*3)*('WEEKLY INPUT'!P205/90)+(P205*0.15)*('WEEKLY INPUT'!P205/90)+Q205*0.25) | U205: =IF($A205="","",$T205*(1+($3-'WEEKLY INPUT'!R205)*0.10)*$R205*$S205*1.0) | V205: =IF($A205="","",$T205*(1+($3-'WEEKLY INPUT'!S205)*0.10)*$R205*$S205*0.975) | W205: =IF($A205="","",$T205*(1+($3-'WEEKLY INPUT'!T205)*0.10)*$R205*$S205*0.95) | X205: =IF($A205="","",$T205*(1+($3-'WEEKLY INPUT'!U205)*0.10)*$R205*$S205*0.925) | Y205: =IF($A205="","",$T205*(1+($3-'WEEKLY INPUT'!V205)*0.10)*$R205*$S205*0.9) | Z205: =IF($A205="","",$T205*(1+($3-'WEEKLY INPUT'!W205)*0.10)*$R205*$S205*0.875) | AA205: =IF($A205="","",$T205*(1+($3-'WEEKLY INPUT'!X205)*0.10)*$R205*$S205*0.85) | AB205: =IF($A205="","",$T205*(1+($3-'WEEKLY INPUT'!Y205)*0.10)*$R205*$S205*0.825) | AC205: =SUM(U205:AB205) | AD205: =SUM(U205:Z205) | AE205: =IFERROR(AD205/D205,0) | AF205: =MAX(0,1-R205) | AG205: =IFERROR((H205+I205)*R205*(1+0.10*(3-'WEEKLY INPUT'!R205)),"") | AH205: =IFERROR(AG205/SUMPRODUCT($AG$6:$AG$205),"") | AI205: =IFERROR(AD205*(1-AF205*0.5)*(1+0.15*AE205),0) | AJ205: =IF(A205="","",RANK(AI205,$AI$6:$AI$205,0)) | AK205: =IFERROR('WEEKLY INPUT'!Z205,"")

Sheet 8GW PROJECTIONS
A1: 8-Gameweek Projection Board
A2: Formula-driven decision support — not an official FPL prediction.
A3: Ranking logic | B3: Players are ranked by 8GW xP, with a separate 6GW value metric. Use the board to spot medium-term moves rather than chasing one fixture.
A5: Rank | B5: Player | C5: Club | D5: Pos | E5: Price | F5: GW1 | G5: GW2 | H5: GW3 | I5: GW4 | J5: GW5 | K5: GW6 | L5: GW7 | M5: GW8 | N5: 8GW xP | O5: 6GW xP | P5: xP/£m | Q5: Minutes risk | R5: Captain prob | S5: Decision Score
A6: 1 | B6: =IFERROR(INDEX('PLAYER MODEL'!$A$6:$A$205,MATCH(LARGE('PLAYER MODEL'!$AC$6:$AC$205,$A6),'PLAYER MODEL'!$AC$6:$AC$205,0)),"") | C6: =IFERROR(XLOOKUP(B6,'PLAYER MODEL'!A:A,'PLAYER MODEL'!B:B),"") | D6: =IFERROR(XLOOKUP(B6,'PLAYER MODEL'!A:A,'PLAYER MODEL'!C:C),"") | E6: =IFERROR(XLOOKUP(B6,'PLAYER MODEL'!A:A,'PLAYER MODEL'!D:D),0) | F6: =IFERROR(XLOOKUP($B6,'PLAYER MODEL'!$A:$A,'PLAYER MODEL'!$U:$U),0) | G6: =IFERROR(XLOOKUP($B6,'PLAYER MODEL'!$A:$A,'PLAYER MODEL'!$V:$V),0) | H6: =IFERROR(XLOOKUP($B6,'PLAYER MODEL'!$A:$A,'PLAYER MODEL'!$W:$W),0) | I6: =IFERROR(XLOOKUP($B6,'PLAYER MODEL'!$A:$A,'PLAYER MODEL'!$X:$X),0) | J6: =IFERROR(XLOOKUP($B6,'PLAYER MODEL'!$A:$A,'PLAYER MODEL'!$Y:$Y),0) | K6: =IFERROR(XLOOKUP($B6,'PLAYER MODEL'!$A:$A,'PLAYER MODEL'!$Z:$Z),0) | L6: =IFERROR(XLOOKUP($B6,'PLAYER MODEL'!$A:$A,'PLAYER MODEL'!$AA:$AA),0) | M6: =IFERROR(XLOOKUP($B6,'PLAYER MODEL'!$A:$A,'PLAYER MODEL'!$AB:$AB),0) | N6: =SUM(F6:M6) | O6: =SUM(F6:K6) | P6: =IFERROR(O6/E6,0) | Q6: =IFERROR(XLOOKUP(B6,'PLAYER MODEL'!A:A,'PLAYER MODEL'!AF:AF),0) | R6: =IFERROR(XLOOKUP(B6,'PLAYER MODEL'!A:A,'PLAYER MODEL'!AH:AH),0) | S6: =IFERROR(XLOOKUP(B6,'PLAYER MODEL'!A:A,'PLAYER MODEL'!AI:AI),0)
A7: 2 | B7: =IFERROR(INDEX('PLAYER MODEL'!$A$6:$A$205,MATCH(LARGE('PLAYER MODEL'!$AC$6:$AC$205,$A7),'PLAYER MODEL'!$AC$6:$AC$205,0)),"") | C7: =IFERROR(XLOOKUP(B7,'PLAYER MODEL'!A:A,'PLAYER MODEL'!B:B),"") | D7: =IFERROR(XLOOKUP(B7,'PLAYER MODEL'!A:A,'PLAYER MODEL'!C:C),"") | E7: =IFERROR(XLOOKUP(B7,'PLAYER MODEL'!A:A,'PLAYER MODEL'!D:D),0) | F7: =IFERROR(XLOOKUP($B7,'PLAYER MODEL'!$A:$A,'PLAYER MODEL'!$U:$U),0) | G7: =IFERROR(XLOOKUP($B7,'PLAYER MODEL'!$A:$A,'PLAYER MODEL'!$V:$V),0) | H7: =IFERROR(XLOOKUP($B7,'PLAYER MODEL'!$A:$A,'PLAYER MODEL'!$W:$W),0) | I7: =IFERROR(XLOOKUP($B7,'PLAYER MODEL'!$A:$A,'PLAYER MODEL'!$X:$X),0) | J7: =IFERROR(XLOOKUP($B7,'PLAYER MODEL'!$A:$A,'PLAYER MODEL'!$Y:$Y),0) | K7: =IFERROR(XLOOKUP($B7,'PLAYER MODEL'!$A:$A,'PLAYER MODEL'!$Z:$Z),0) | L7: =IFERROR(XLOOKUP($B7,'PLAYER MODEL'!$A:$A,'PLAYER MODEL'!$AA:$AA),0) | M7: =IFERROR(XLOOKUP($B7,'PLAYER MODEL'!$A:$A,'PLAYER MODEL'!$AB:$AB),0) | N7: =SUM(F7:M7) | O7: =SUM(F7:K7) | P7: =IFERROR(O7/E7,0) | Q7: =IFERROR(XLOOKUP(B7,'PLAYER MODEL'!A:A,'PLAYER MODEL'!AF:AF),0) | R7: =IFERROR(XLOOKUP(B7,'PLAYER MODEL'!A:A,'PLAYER MODEL'!AH:AH),0) | S7: =IFERROR(XLOOKUP(B7,'PLAYER MODEL'!A:A,'PLAYER MODEL'!AI:AI),0)
A8: 3 | B8: =IFERROR(INDEX('PLAYER MODEL'!$A$6:$A$205,MATCH(LARGE('PLAYER MODEL'!$AC$6:$AC$205,$A8),'PLAYER MODEL'!$AC$6:$AC$205,0)),"") | C8: =IFERROR(XLOOKUP(B8,'PLAYER MODEL'!A:A,'PLAYER MODEL'!B:B),"") | D8: =IFERROR(XLOOKUP(B8,'PLAYER MODEL'!A:A,'PLAYER MODEL'!C:C),"") | E8: =IFERROR(XLOOKUP(B8,'PLAYER MODEL'!A:A,'PLAYER MODEL'!D:D),0) | F8: =IFERROR(XLOOKUP($B8,'PLAYER MODEL'!$A:$A,'PLAYER MODEL'!$U:$U),0) | G8: =IFERROR(XLOOKUP($B8,'PLAYER MODEL'!$A:$A,'PLAYER MODEL'!$V:$V),0) | H8: =IFERROR(XLOOKUP($B8,'PLAYER MODEL'!$A:$A,'PLAYER MODEL'!$W:$W),0) | I8: =IFERROR(XLOOKUP($B8,'PLAYER MODEL'!$A:$A,'PLAYER MODEL'!$X:$X),0) | J8: =IFERROR(XLOOKUP($B8,'PLAYER MODEL'!$A:$A,'PLAYER MODEL'!$Y:$Y),0) | K8: =IFERROR(XLOOKUP($B8,'PLAYER MODEL'!$A:$A,'PLAYER MODEL'!$Z:$Z),0) | L8: =IFERROR(XLOOKUP($B8,'PLAYER MODEL'!$A:$A,'PLAYER MODEL'!$AA:$AA),0) | M8: =IFERROR(XLOOKUP($B8,'PLAYER MODEL'!$A:$A,'PLAYER MODEL'!$AB:$AB),0) | N8: =SUM(F8:M8) | O8: =SUM(F8:K8) | P8: =IFERROR(O8/E8,0) | Q8: =IFERROR(XLOOKUP(B8,'PLAYER MODEL'!A:A,'PLAYER MODEL'!AF:AF),0) | R8: =IFERROR(XLOOKUP(B8,'PLAYER MODEL'!A:A,'PLAYER MODEL'!AH:AH),0) | S8: =IFERROR(XLOOKUP(B8,'PLAYER MODEL'!A:A,'PLAYER MODEL'!AI:AI),0)
A9: 4 | B9: =IFERROR(INDEX('PLAYER MODEL'!$A$6:$A$205,MATCH(LARGE('PLAYER MODEL'!$AC$6:$AC$205,$A9),'PLAYER MODEL'!$AC$6:$AC$205,0)),"") | C9: =IFERROR(XLOOKUP(B9,'PLAYER MODEL'!A:A,'PLAYER MODEL'!B:B),"") | D9: =IFERROR(XLOOKUP(B9,'PLAYER MODEL'!A:A,'PLAYER MODEL'!C:C),"") | E9: =IFERROR(XLOOKUP(B9,'PLAYER MODEL'!A:A,'PLAYER MODEL'!D:D),0) | F9: =IFERROR(XLOOKUP($B9,'PLAYER MODEL'!$A:$A,'PLAYER MODEL'!$U:$U),0) | G9: =IFERROR(XLOOKUP($B9,'PLAYER MODEL'!$A:$A,'PLAYER MODEL'!$V:$V),0) | H9: =IFERROR(XLOOKUP($B9,'PLAYER MODEL'!$A:$A,'PLAYER MODEL'!$W:$W),0) | I9: =IFERROR(XLOOKUP($B9,'PLAYER MODEL'!$A:$A,'PLAYER MODEL'!$X:$X),0) | J9: =IFERROR(XLOOKUP($B9,'PLAYER MODEL'!$A:$A,'PLAYER MODEL'!$Y:$Y),0) | K9: =IFERROR(XLOOKUP($B9,'PLAYER MODEL'!$A:$A,'PLAYER MODEL'!$Z:$Z),0) | L9: =IFERROR(XLOOKUP($B9,'PLAYER MODEL'!$A:$A,'PLAYER MODEL'!$AA:$AA),0) | M9: =IFERROR(XLOOKUP($B9,'PLAYER MODEL'!$A:$A,'PLAYER MODEL'!$AB:$AB),0) | N9: =SUM(F9:M9) | O9: =SUM(F9:K9) | P9: =IFERROR(O9/E9,0) | Q9: =IFERROR(XLOOKUP(B9,'PLAYER MODEL'!A:A,'PLAYER MODEL'!AF:AF),0) | R9: =IFERROR(XLOOKUP(B9,'PLAYER MODEL'!A:A,'PLAYER MODEL'!AH:AH),0) | S9: =IFERROR(XLOOKUP(B9,'PLAYER MODEL'!A:A,'PLAYER MODEL'!AI:AI),0)
A10: 5 | B10: =IFERROR(INDEX('PLAYER MODEL'!$A$6:$A$205,MATCH(LARGE('PLAYER MODEL'!$AC$6:$AC$205,$A10),'PLAYER MODEL'!$AC$6:$AC$205,0)),"") | C10: =IFERROR(XLOOKUP(B10,'PLAYER MODEL'!A:A,'PLAYER MODEL'!B:B),"") | D10: =IFERROR(XLOOKUP(B10,'PLAYER MODEL'!A:A,'PLAYER MODEL'!C:C),"") | E10: =IFERROR(XLOOKUP(B10,'PLAYER MODEL'!A:A,'PLAYER MODEL'!D:D),0) | F10: =IFERROR(XLOOKUP($B10,'PLAYER MODEL'!$A:$A,'PLAYER MODEL'!$U:$U),0) | G10: =IFERROR(XLOOKUP($B10,'PLAYER MODEL'!$A:$A,'PLAYER MODEL'!$V:$V),0) | H10: =IFERROR(XLOOKUP($B10,'PLAYER MODEL'!$A:$A,'PLAYER MODEL'!$W:$W),0) | I10: =IFERROR(XLOOKUP($B10,'PLAYER MODEL'!$A:$A,'PLAYER MODEL'!$X:$X),0) | J10: =IFERROR(XLOOKUP($B10,'PLAYER MODEL'!$A:$A,'PLAYER MODEL'!$Y:$Y),0) | K10: =IFERROR(XLOOKUP($B10,'PLAYER MODEL'!$A:$A,'PLAYER MODEL'!$Z:$Z),0) | L10: =IFERROR(XLOOKUP($B10,'PLAYER MODEL'!$A:$A,'PLAYER MODEL'!$AA:$AA),0) | M10: =IFERROR(XLOOKUP($B10,'PLAYER MODEL'!$A:$A,'PLAYER MODEL'!$AB:$AB),0) | N10: =SUM(F10:M10) | O10: =SUM(F10:K10) | P10: =IFERROR(O10/E10,0) | Q10: =IFERROR(XLOOKUP(B10,'PLAYER MODEL'!A:A,'PLAYER MODEL'!AF:AF),0) | R10: =IFERROR(XLOOKUP(B10,'PLAYER MODEL'!A:A,'PLAYER MODEL'!AH:AH),0) | S10: =IFERROR(XLOOKUP(B10,'PLAYER MODEL'!A:A,'PLAYER MODEL'!AI:AI),0)
A11: 6 | B11: =IFERROR(INDEX('PLAYER MODEL'!$A$6:$A$205,MATCH(LARGE('PLAYER MODEL'!$AC$6:$AC$205,$A11),'PLAYER MODEL'!$AC$6:$AC$205,0)),"") | C11: =IFERROR(XLOOKUP(B11,'PLAYER MODEL'!A:A,'PLAYER MODEL'!B:B),"") | D11: =IFERROR(XLOOKUP(B11,'PLAYER MODEL'!A:A,'PLAYER MODEL'!C:C),"") | E11: =IFERROR(XLOOKUP(B11,'PLAYER MODEL'!A:A,'PLAYER MODEL'!D:D),0) | F11: =IFERROR(XLOOKUP($B11,'PLAYER MODEL'!$A:$A,'PLAYER MODEL'!$U:$U),0) | G11: =IFERROR(XLOOKUP($B11,'PLAYER MODEL'!$A:$A,'PLAYER MODEL'!$V:$V),0) | H11: =IFERROR(XLOOKUP($B11,'PLAYER MODEL'!$A:$A,'PLAYER MODEL'!$W:$W),0) | I11: =IFERROR(XLOOKUP($B11,'PLAYER MODEL'!$A:$A,'PLAYER MODEL'!$X:$X),0) | J11: =IFERROR(XLOOKUP($B11,'PLAYER MODEL'!$A:$A,'PLAYER MODEL'!$Y:$Y),0) | K11: =IFERROR(XLOOKUP($B11,'PLAYER MODEL'!$A:$A,'PLAYER MODEL'!$Z:$Z),0) | L11: =IFERROR(XLOOKUP($B11,'PLAYER MODEL'!$A:$A,'PLAYER MODEL'!$AA:$AA),0) | M11: =IFERROR(XLOOKUP($B11,'PLAYER MODEL'!$A:$A,'PLAYER MODEL'!$AB:$AB),0) | N11: =SUM(F11:M11) | O11: =SUM(F11:K11) | P11: =IFERROR(O11/E11,0) | Q11: =IFERROR(XLOOKUP(B11,'PLAYER MODEL'!A:A,'PLAYER MODEL'!AF:AF),0) | R11: =IFERROR(XLOOKUP(B11,'PLAYER MODEL'!A:A,'PLAYER MODEL'!AH:AH),0) | S11: =IFERROR(XLOOKUP(B11,'PLAYER MODEL'!A:A,'PLAYER MODEL'!AI:AI),0)
A12: 7 | B12: =IFERROR(INDEX('PLAYER MODEL'!$A$6:$A$205,MATCH(LARGE('PLAYER MODEL'!$AC$6:$AC$205,$A12),'PLAYER MODEL'!$AC$6:$AC$205,0)),"") | C12: =IFERROR(XLOOKUP(B12,'PLAYER MODEL'!A:A,'PLAYER MODEL'!B:B),"") | D12: =IFERROR(XLOOKUP(B12,'PLAYER MODEL'!A:A,'PLAYER MODEL'!C:C),"") | E12: =IFERROR(XLOOKUP(B12,'PLAYER MODEL'!A:A,'PLAYER MODEL'!D:D),0) | F12: =IFERROR(XLOOKUP($B12,'PLAYER MODEL'!$A:$A,'PLAYER MODEL'!$U:$U),0) | G12: =IFERROR(XLOOKUP($B12,'PLAYER MODEL'!$A:$A,'PLAYER MODEL'!$V:$V),0) | H12: =IFERROR(XLOOKUP($B12,'PLAYER MODEL'!$A:$A,'PLAYER MODEL'!$W:$W),0) | I12: =IFERROR(XLOOKUP($B12,'PLAYER MODEL'!$A:$A,'PLAYER MODEL'!$X:$X),0) | J12: =IFERROR(XLOOKUP($B12,'PLAYER MODEL'!$A:$A,'PLAYER MODEL'!$Y:$Y),0) | K12: =IFERROR(XLOOKUP($B12,'PLAYER MODEL'!$A:$A,'PLAYER MODEL'!$Z:$Z),0) | L12: =IFERROR(XLOOKUP($B12,'PLAYER MODEL'!$A:$A,'PLAYER MODEL'!$AA:$AA),0) | M12: =IFERROR(XLOOKUP($B12,'PLAYER MODEL'!$A:$A,'PLAYER MODEL'!$AB:$AB),0) | N12: =SUM(F12:M12) | O12: =SUM(F12:K12) | P12: =IFERROR(O12/E12,0) | Q12: =IFERROR(XLOOKUP(B12,'PLAYER MODEL'!A:A,'PLAYER MODEL'!AF:AF),0) | R12: =IFERROR(XLOOKUP(B12,'PLAYER MODEL'!A:A,'PLAYER MODEL'!AH:AH),0) | S12: =IFERROR(XLOOKUP(B12,'PLAYER MODEL'!A:A,'PLAYER MODEL'!AI:AI),0)
A13: 8 | B13: =IFERROR(INDEX('PLAYER MODEL'!$A$6:$A$205,MATCH(LARGE('PLAYER MODEL'!$AC$6:$AC$205,$A13),'PLAYER MODEL'!$AC$6:$AC$205,0)),"") | C13: =IFERROR(XLOOKUP(B13,'PLAYER MODEL'!A:A,'PLAYER MODEL'!B:B),"") | D13: =IFERROR(XLOOKUP(B13,'PLAYER MODEL'!A:A,'PLAYER MODEL'!C:C),"") | E13: =IFERROR(XLOOKUP(B13,'PLAYER MODEL'!A:A,'PLAYER MODEL'!D:D),0) | F13: =IFERROR(XLOOKUP($B13,'PLAYER MODEL'!$A:$A,'PLAYER MODEL'!$U:$U),0) | G13: =IFERROR(XLOOKUP($B13,'PLAYER MODEL'!$A:$A,'PLAYER MODEL'!$V:$V),0) | H13: =IFERROR(XLOOKUP($B13,'PLAYER MODEL'!$A:$A,'PLAYER MODEL'!$W:$W),0) | I13: =IFERROR(XLOOKUP($B13,'PLAYER MODEL'!$A:$A,'PLAYER MODEL'!$X:$X),0) | J13: =IFERROR(XLOOKUP($B13,'PLAYER MODEL'!$A:$A,'PLAYER MODEL'!$Y:$Y),0) | K13: =IFERROR(XLOOKUP($B13,'PLAYER MODEL'!$A:$A,'PLAYER MODEL'!$Z:$Z),0) | L13: =IFERROR(XLOOKUP($B13,'PLAYER MODEL'!$A:$A,'PLAYER MODEL'!$AA:$AA),0) | M13: =IFERROR(XLOOKUP($B13,'PLAYER MODEL'!$A:$A,'PLAYER MODEL'!$AB:$AB),0) | N13: =SUM(F13:M13) | O13: =SUM(F13:K13) | P13: =IFERROR(O13/E13,0) | Q13: =IFERROR(XLOOKUP(B13,'PLAYER MODEL'!A:A,'PLAYER MODEL'!AF:AF),0) | R13: =IFERROR(XLOOKUP(B13,'PLAYER MODEL'!A:A,'PLAYER MODEL'!AH:AH),0) | S13: =IFERROR(XLOOKUP(B13,'PLAYER MODEL'!A:A,'PLAYER MODEL'!AI:AI),0)
A14: 9 | B14: =IFERROR(INDEX('PLAYER MODEL'!$A$6:$A$205,MATCH(LARGE('PLAYER MODEL'!$AC$6:$AC$205,$A14),'PLAYER MODEL'!$AC$6:$AC$205,0)),"") | C14: =IFERROR(XLOOKUP(B14,'PLAYER MODEL'!A:A,'PLAYER MODEL'!B:B),"") | D14: =IFERROR(XLOOKUP(B14,'PLAYER MODEL'!A:A,'PLAYER MODEL'!C:C),"") | E14: =IFERROR(XLOOKUP(B14,'PLAYER MODEL'!A:A,'PLAYER MODEL'!D:D),0) | F14: =IFERROR(XLOOKUP($B14,'PLAYER MODEL'!$A:$A,'PLAYER MODEL'!$U:$U),0) | G14: =IFERROR(XLOOKUP($B14,'PLAYER MODEL'!$A:$A,'PLAYER MODEL'!$V:$V),0) | H14: =IFERROR(XLOOKUP($B14,'PLAYER MODEL'!$A:$A,'PLAYER MODEL'!$W:$W),0) | I14: =IFERROR(XLOOKUP($B14,'PLAYER MODEL'!$A:$A,'PLAYER MODEL'!$X:$X),0) | J14: =IFERROR(XLOOKUP($B14,'PLAYER MODEL'!$A:$A,'PLAYER MODEL'!$Y:$Y),0) | K14: =IFERROR(XLOOKUP($B14,'PLAYER MODEL'!$A:$A,'PLAYER MODEL'!$Z:$Z),0) | L14: =IFERROR(XLOOKUP($B14,'PLAYER MODEL'!$A:$A,'PLAYER MODEL'!$AA:$AA),0) | M14: =IFERROR(XLOOKUP($B14,'PLAYER MODEL'!$A:$A,'PLAYER MODEL'!$AB:$AB),0) | N14: =SUM(F14:M14) | O14: =SUM(F14:K14) | P14: =IFERROR(O14/E14,0) | Q14: =IFERROR(XLOOKUP(B14,'PLAYER MODEL'!A:A,'PLAYER MODEL'!AF:AF),0) | R14: =IFERROR(XLOOKUP(B14,'PLAYER MODEL'!A:A,'PLAYER MODEL'!AH:AH),0) | S14: =IFERROR(XLOOKUP(B14,'PLAYER MODEL'!A:A,'PLAYER MODEL'!AI:AI),0)
A15: 10 | B15: =IFERROR(INDEX('PLAYER MODEL'!$A$6:$A$205,MATCH(LARGE('PLAYER MODEL'!$AC$6:$AC$205,$A15),'PLAYER MODEL'!$AC$6:$AC$205,0)),"") | C15: =IFERROR(XLOOKUP(B15,'PLAYER MODEL'!A:A,'PLAYER MODEL'!B:B),"") | D15: =IFERROR(XLOOKUP(B15,'PLAYER MODEL'!A:A,'PLAYER MODEL'!C:C),"") | E15: =IFERROR(XLOOKUP(B15,'PLAYER MODEL'!A:A,'PLAYER MODEL'!D:D),0) | F15: =IFERROR(XLOOKUP($B15,'PLAYER MODEL'!$A:$A,'PLAYER MODEL'!$U:$U),0) | G15: =IFERROR(XLOOKUP($B15,'PLAYER MODEL'!$A:$A,'PLAYER MODEL'!$V:$V),0) | H15: =IFERROR(XLOOKUP($B15,'PLAYER MODEL'!$A:$A,'PLAYER MODEL'!$W:$W),0) | I15: =IFERROR(XLOOKUP($B15,'PLAYER MODEL'!$A:$A,'PLAYER MODEL'!$X:$X),0) | J15: =IFERROR(XLOOKUP($B15,'PLAYER MODEL'!$A:$A,'PLAYER MODEL'!$Y:$Y),0) | K15: =IFERROR(XLOOKUP($B15,'PLAYER MODEL'!$A:$A,'PLAYER MODEL'!$Z:$Z),0) | L15: =IFERROR(XLOOKUP($B15,'PLAYER MODEL'!$A:$A,'PLAYER MODEL'!$AA:$AA),0) | M15: =IFERROR(XLOOKUP($B15,'PLAYER MODEL'!$A:$A,'PLAYER MODEL'!$AB:$AB),0) | N15: =SUM(F15:M15) | O15: =SUM(F15:K15) | P15: =IFERROR(O15/E15,0) | Q15: =IFERROR(XLOOKUP(B15,'PLAYER MODEL'!A:A,'PLAYER MODEL'!AF:AF),0) | R15: =IFERROR(XLOOKUP(B15,'PLAYER MODEL'!A:A,'PLAYER MODEL'!AH:AH),0) | S15: =IFERROR(XLOOKUP(B15,'PLAYER MODEL'!A:A,'PLAYER MODEL'!AI:AI),0)
A16: 11 | B16: =IFERROR(INDEX('PLAYER MODEL'!$A$6:$A$205,MATCH(LARGE('PLAYER MODEL'!$AC$6:$AC$205,$A16),'PLAYER MODEL'!$AC$6:$AC$205,0)),"") | C16: =IFERROR(XLOOKUP(B16,'PLAYER MODEL'!A:A,'PLAYER MODEL'!B:B),"") | D16: =IFERROR(XLOOKUP(B16,'PLAYER MODEL'!A:A,'PLAYER MODEL'!C:C),"") | E16: =IFERROR(XLOOKUP(B16,'PLAYER MODEL'!A:A,'PLAYER MODEL'!D:D),0) | F16: =IFERROR(XLOOKUP($B16,'PLAYER MODEL'!$A:$A,'PLAYER MODEL'!$U:$U),0) | G16: =IFERROR(XLOOKUP($B16,'PLAYER MODEL'!$A:$A,'PLAYER MODEL'!$V:$V),0) | H16: =IFERROR(XLOOKUP($B16,'PLAYER MODEL'!$A:$A,'PLAYER MODEL'!$W:$W),0) | I16: =IFERROR(XLOOKUP($B16,'PLAYER MODEL'!$A:$A,'PLAYER MODEL'!$X:$X),0) | J16: =IFERROR(XLOOKUP($B16,'PLAYER MODEL'!$A:$A,'PLAYER MODEL'!$Y:$Y),0) | K16: =IFERROR(XLOOKUP($B16,'PLAYER MODEL'!$A:$A,'PLAYER MODEL'!$Z:$Z),0) | L16: =IFERROR(XLOOKUP($B16,'PLAYER MODEL'!$A:$A,'PLAYER MODEL'!$AA:$AA),0) | M16: =IFERROR(XLOOKUP($B16,'PLAYER MODEL'!$A:$A,'PLAYER MODEL'!$AB:$AB),0) | N16: =SUM(F16:M16) | O16: =SUM(F16:K16) | P16: =IFERROR(O16/E16,0) | Q16: =IFERROR(XLOOKUP(B16,'PLAYER MODEL'!A:A,'PLAYER MODEL'!AF:AF),0) | R16: =IFERROR(XLOOKUP(B16,'PLAYER MODEL'!A:A,'PLAYER MODEL'!AH:AH),0) | S16: =IFERROR(XLOOKUP(B16,'PLAYER MODEL'!A:A,'PLAYER MODEL'!AI:AI),0)
A17: 12 | B17: =IFERROR(INDEX('PLAYER MODEL'!$A$6:$A$205,MATCH(LARGE('PLAYER MODEL'!$AC$6:$AC$205,$A17),'PLAYER MODEL'!$AC$6:$AC$205,0)),"") | C17: =IFERROR(XLOOKUP(B17,'PLAYER MODEL'!A:A,'PLAYER MODEL'!B:B),"") | D17: =IFERROR(XLOOKUP(B17,'PLAYER MODEL'!A:A,'PLAYER MODEL'!C:C),"") | E17: =IFERROR(XLOOKUP(B17,'PLAYER MODEL'!A:A,'PLAYER MODEL'!D:D),0) | F17: =IFERROR(XLOOKUP($B17,'PLAYER MODEL'!$A:$A,'PLAYER MODEL'!$U:$U),0) | G17: =IFERROR(XLOOKUP($B17,'PLAYER MODEL'!$A:$A,'PLAYER MODEL'!$V:$V),0) | H17: =IFERROR(XLOOKUP($B17,'PLAYER MODEL'!$A:$A,'PLAYER MODEL'!$W:$W),0) | I17: =IFERROR(XLOOKUP($B17,'PLAYER MODEL'!$A:$A,'PLAYER MODEL'!$X:$X),0) | J17: =IFERROR(XLOOKUP($B17,'PLAYER MODEL'!$A:$A,'PLAYER MODEL'!$Y:$Y),0) | K17: =IFERROR(XLOOKUP($B17,'PLAYER MODEL'!$A:$A,'PLAYER MODEL'!$Z:$Z),0) | L17: =IFERROR(XLOOKUP($B17,'PLAYER MODEL'!$A:$A,'PLAYER MODEL'!$AA:$AA),0) | M17: =IFERROR(XLOOKUP($B17,'PLAYER MODEL'!$A:$A,'PLAYER MODEL'!$AB:$AB),0) | N17: =SUM(F17:M17) | O17: =SUM(F17:K17) | P17: =IFERROR(O17/E17,0) | Q17: =IFERROR(XLOOKUP(B17,'PLAYER MODEL'!A:A,'PLAYER MODEL'!AF:AF),0) | R17: =IFERROR(XLOOKUP(B17,'PLAYER MODEL'!A:A,'PLAYER MODEL'!AH:AH),0) | S17: =IFERROR(XLOOKUP(B17,'PLAYER MODEL'!A:A,'PLAYER MODEL'!AI:AI),0)
... A35: 30 | B35: =IFERROR(INDEX('PLAYER MODEL'!$A$6:$A$205,MATCH(LARGE('PLAYER MODEL'!$AC$6:$AC$205,$A35),'PLAYER MODEL'!$AC$6:$AC$205,0)),"") | C35: =IFERROR(XLOOKUP(B35,'PLAYER MODEL'!A:A,'PLAYER MODEL'!B:B),"") | D35: =IFERROR(XLOOKUP(B35,'PLAYER MODEL'!A:A,'PLAYER MODEL'!C:C),"") | E35: =IFERROR(XLOOKUP(B35,'PLAYER MODEL'!A:A,'PLAYER MODEL'!D:D),0) | F35: =IFERROR(XLOOKUP($B35,'PLAYER MODEL'!$A:$A,'PLAYER MODEL'!$U:$U),0) | G35: =IFERROR(XLOOKUP($B35,'PLAYER MODEL'!$A:$A,'PLAYER MODEL'!$V:$V),0) | H35: =IFERROR(XLOOKUP($B35,'PLAYER MODEL'!$A:$A,'PLAYER MODEL'!$W:$W),0) | I35: =IFERROR(XLOOKUP($B35,'PLAYER MODEL'!$A:$A,'PLAYER MODEL'!$X:$X),0) | J35: =IFERROR(XLOOKUP($B35,'PLAYER MODEL'!$A:$A,'PLAYER MODEL'!$Y:$Y),0) | K35: =IFERROR(XLOOKUP($B35,'PLAYER MODEL'!$A:$A,'PLAYER MODEL'!$Z:$Z),0) | L35: =IFERROR(XLOOKUP($B35,'PLAYER MODEL'!$A:$A,'PLAYER MODEL'!$AA:$AA),0) | M35: =IFERROR(XLOOKUP($B35,'PLAYER MODEL'!$A:$A,'PLAYER MODEL'!$AB:$AB),0) | N35: =SUM(F35:M35) | O35: =SUM(F35:K35) | P35: =IFERROR(O35/E35,0) | Q35: =IFERROR(XLOOKUP(B35,'PLAYER MODEL'!A:A,'PLAYER MODEL'!AF:AF),0) | R35: =IFERROR(XLOOKUP(B35,'PLAYER MODEL'!A:A,'PLAYER MODEL'!AH:AH),0) | S35: =IFERROR(XLOOKUP(B35,'PLAYER MODEL'!A:A,'PLAYER MODEL'!AI:AI),0)

Sheet TRANSFER EV
A1: Transfer Expected Value Engine
A2: Formula-driven decision support — not an official FPL prediction.
A3: Use this for actual transfer decisions | B3: Enter OUT and IN players, number of transfers taken this week, and any qualitative reason. The engine compares 6GW and 8GW projections and subtracts the hit.
A5: GW | B5: OUT | C5: IN | D5: Free transfers available | E5: Total transfers taken | F5: Hit cost | G5: OUT 6GW xP | H5: IN 6GW xP | I5: 6GW gross gain | J5: Net 6GW EV | K5: OUT 8GW xP | L5: IN 8GW xP | M5: 8GW gross gain | N5: Net 8GW EV | O5: Price delta | P5: Fixture/role reason | Q5: Decision
F6: =MAX(0,E6-D6)*4 | G6: =IFERROR(XLOOKUP(B6,'PLAYER MODEL'!A:A,'PLAYER MODEL'!AD:AD),0) | H6: =IFERROR(XLOOKUP(C6,'PLAYER MODEL'!A:A,'PLAYER MODEL'!AD:AD),0) | I6: =H6-G6 | J6: =I6-F6 | K6: =IFERROR(XLOOKUP(B6,'PLAYER MODEL'!A:A,'PLAYER MODEL'!AC:AC),0) | L6: =IFERROR(XLOOKUP(C6,'PLAYER MODEL'!A:A,'PLAYER MODEL'!AC:AC),0) | M6: =L6-K6 | N6: =M6-F6 | O6: =IFERROR(XLOOKUP(C6,'PLAYER MODEL'!A:A,'PLAYER MODEL'!D:D)-XLOOKUP(B6,'PLAYER MODEL'!A:A,'PLAYER MODEL'!D:D),0) | Q6: =IF(J6>0,"Positive 6GW EV",IF(N6>0,"Positive 8GW EV","No clear EV"))
F7: =MAX(0,E7-D7)*4 | G7: =IFERROR(XLOOKUP(B7,'PLAYER MODEL'!A:A,'PLAYER MODEL'!AD:AD),0) | H7: =IFERROR(XLOOKUP(C7,'PLAYER MODEL'!A:A,'PLAYER MODEL'!AD:AD),0) | I7: =H7-G7 | J7: =I7-F7 | K7: =IFERROR(XLOOKUP(B7,'PLAYER MODEL'!A:A,'PLAYER MODEL'!AC:AC),0) | L7: =IFERROR(XLOOKUP(C7,'PLAYER MODEL'!A:A,'PLAYER MODEL'!AC:AC),0) | M7: =L7-K7 | N7: =M7-F7 | O7: =IFERROR(XLOOKUP(C7,'PLAYER MODEL'!A:A,'PLAYER MODEL'!D:D)-XLOOKUP(B7,'PLAYER MODEL'!A:A,'PLAYER MODEL'!D:D),0) | Q7: =IF(J7>0,"Positive 6GW EV",IF(N7>0,"Positive 8GW EV","No clear EV"))
F8: =MAX(0,E8-D8)*4 | G8: =IFERROR(XLOOKUP(B8,'PLAYER MODEL'!A:A,'PLAYER MODEL'!AD:AD),0) | H8: =IFERROR(XLOOKUP(C8,'PLAYER MODEL'!A:A,'PLAYER MODEL'!AD:AD),0) | I8: =H8-G8 | J8: =I8-F8 | K8: =IFERROR(XLOOKUP(B8,'PLAYER MODEL'!A:A,'PLAYER MODEL'!AC:AC),0) | L8: =IFERROR(XLOOKUP(C8,'PLAYER MODEL'!A:A,'PLAYER MODEL'!AC:AC),0) | M8: =L8-K8 | N8: =M8-F8 | O8: =IFERROR(XLOOKUP(C8,'PLAYER MODEL'!A:A,'PLAYER MODEL'!D:D)-XLOOKUP(B8,'PLAYER MODEL'!A:A,'PLAYER MODEL'!D:D),0) | Q8: =IF(J8>0,"Positive 6GW EV",IF(N8>0,"Positive 8GW EV","No clear EV"))
F9: =MAX(0,E9-D9)*4 | G9: =IFERROR(XLOOKUP(B9,'PLAYER MODEL'!A:A,'PLAYER MODEL'!AD:AD),0) | H9: =IFERROR(XLOOKUP(C9,'PLAYER MODEL'!A:A,'PLAYER MODEL'!AD:AD),0) | I9: =H9-G9 | J9: =I9-F9 | K9: =IFERROR(XLOOKUP(B9,'PLAYER MODEL'!A:A,'PLAYER MODEL'!AC:AC),0) | L9: =IFERROR(XLOOKUP(C9,'PLAYER MODEL'!A:A,'PLAYER MODEL'!AC:AC),0) | M9: =L9-K9 | N9: =M9-F9 | O9: =IFERROR(XLOOKUP(C9,'PLAYER MODEL'!A:A,'PLAYER MODEL'!D:D)-XLOOKUP(B9,'PLAYER MODEL'!A:A,'PLAYER MODEL'!D:D),0) | Q9: =IF(J9>0,"Positive 6GW EV",IF(N9>0,"Positive 8GW EV","No clear EV"))
F10: =MAX(0,E10-D10)*4 | G10: =IFERROR(XLOOKUP(B10,'PLAYER MODEL'!A:A,'PLAYER MODEL'!AD:AD),0) | H10: =IFERROR(XLOOKUP(C10,'PLAYER MODEL'!A:A,'PLAYER MODEL'!AD:AD),0) | I10: =H10-G10 | J10: =I10-F10 | K10: =IFERROR(XLOOKUP(B10,'PLAYER MODEL'!A:A,'PLAYER MODEL'!AC:AC),0) | L10: =IFERROR(XLOOKUP(C10,'PLAYER MODEL'!A:A,'PLAYER MODEL'!AC:AC),0) | M10: =L10-K10 | N10: =M10-F10 | O10: =IFERROR(XLOOKUP(C10,'PLAYER MODEL'!A:A,'PLAYER MODEL'!D:D)-XLOOKUP(B10,'PLAYER MODEL'!A:A,'PLAYER MODEL'!D:D),0) | Q10: =IF(J10>0,"Positive 6GW EV",IF(N10>0,"Positive 8GW EV","No clear EV"))
F11: =MAX(0,E11-D11)*4 | G11: =IFERROR(XLOOKUP(B11,'PLAYER MODEL'!A:A,'PLAYER MODEL'!AD:AD),0) | H11: =IFERROR(XLOOKUP(C11,'PLAYER MODEL'!A:A,'PLAYER MODEL'!AD:AD),0) | I11: =H11-G11 | J11: =I11-F11 | K11: =IFERROR(XLOOKUP(B11,'PLAYER MODEL'!A:A,'PLAYER MODEL'!AC:AC),0) | L11: =IFERROR(XLOOKUP(C11,'PLAYER MODEL'!A:A,'PLAYER MODEL'!AC:AC),0) | M11: =L11-K11 | N11: =M11-F11 | O11: =IFERROR(XLOOKUP(C11,'PLAYER MODEL'!A:A,'PLAYER MODEL'!D:D)-XLOOKUP(B11,'PLAYER MODEL'!A:A,'PLAYER MODEL'!D:D),0) | Q11: =IF(J11>0,"Positive 6GW EV",IF(N11>0,"Positive 8GW EV","No clear EV"))
F12: =MAX(0,E12-D12)*4 | G12: =IFERROR(XLOOKUP(B12,'PLAYER MODEL'!A:A,'PLAYER MODEL'!AD:AD),0) | H12: =IFERROR(XLOOKUP(C12,'PLAYER MODEL'!A:A,'PLAYER MODEL'!AD:AD),0) | I12: =H12-G12 | J12: =I12-F12 | K12: =IFERROR(XLOOKUP(B12,'PLAYER MODEL'!A:A,'PLAYER MODEL'!AC:AC),0) | L12: =IFERROR(XLOOKUP(C12,'PLAYER MODEL'!A:A,'PLAYER MODEL'!AC:AC),0) | M12: =L12-K12 | N12: =M12-F12 | O12: =IFERROR(XLOOKUP(C12,'PLAYER MODEL'!A:A,'PLAYER MODEL'!D:D)-XLOOKUP(B12,'PLAYER MODEL'!A:A,'PLAYER MODEL'!D:D),0) | Q12: =IF(J12>0,"Positive 6GW EV",IF(N12>0,"Positive 8GW EV","No clear EV"))
F13: =MAX(0,E13-D13)*4 | G13: =IFERROR(XLOOKUP(B13,'PLAYER MODEL'!A:A,'PLAYER MODEL'!AD:AD),0) | H13: =IFERROR(XLOOKUP(C13,'PLAYER MODEL'!A:A,'PLAYER MODEL'!AD:AD),0) | I13: =H13-G13 | J13: =I13-F13 | K13: =IFERROR(XLOOKUP(B13,'PLAYER MODEL'!A:A,'PLAYER MODEL'!AC:AC),0) | L13: =IFERROR(XLOOKUP(C13,'PLAYER MODEL'!A:A,'PLAYER MODEL'!AC:AC),0) | M13: =L13-K13 | N13: =M13-F13 | O13: =IFERROR(XLOOKUP(C13,'PLAYER MODEL'!A:A,'PLAYER MODEL'!D:D)-XLOOKUP(B13,'PLAYER MODEL'!A:A,'PLAYER MODEL'!D:D),0) | Q13: =IF(J13>0,"Positive 6GW EV",IF(N13>0,"Positive 8GW EV","No clear EV"))
F14: =MAX(0,E14-D14)*4 | G14: =IFERROR(XLOOKUP(B14,'PLAYER MODEL'!A:A,'PLAYER MODEL'!AD:AD),0) | H14: =IFERROR(XLOOKUP(C14,'PLAYER MODEL'!A:A,'PLAYER MODEL'!AD:AD),0) | I14: =H14-G14 | J14: =I14-F14 | K14: =IFERROR(XLOOKUP(B14,'PLAYER MODEL'!A:A,'PLAYER MODEL'!AC:AC),0) | L14: =IFERROR(XLOOKUP(C14,'PLAYER MODEL'!A:A,'PLAYER MODEL'!AC:AC),0) | M14: =L14-K14 | N14: =M14-F14 | O14: =IFERROR(XLOOKUP(C14,'PLAYER MODEL'!A:A,'PLAYER MODEL'!D:D)-XLOOKUP(B14,'PLAYER MODEL'!A:A,'PLAYER MODEL'!D:D),0) | Q14: =IF(J14>0,"Positive 6GW EV",IF(N14>0,"Positive 8GW EV","No clear EV"))
F15: =MAX(0,E15-D15)*4 | G15: =IFERROR(XLOOKUP(B15,'PLAYER MODEL'!A:A,'PLAYER MODEL'!AD:AD),0) | H15: =IFERROR(XLOOKUP(C15,'PLAYER MODEL'!A:A,'PLAYER MODEL'!AD:AD),0) | I15: =H15-G15 | J15: =I15-F15 | K15: =IFERROR(XLOOKUP(B15,'PLAYER MODEL'!A:A,'PLAYER MODEL'!AC:AC),0) | L15: =IFERROR(XLOOKUP(C15,'PLAYER MODEL'!A:A,'PLAYER MODEL'!AC:AC),0) | M15: =L15-K15 | N15: =M15-F15 | O15: =IFERROR(XLOOKUP(C15,'PLAYER MODEL'!A:A,'PLAYER MODEL'!D:D)-XLOOKUP(B15,'PLAYER MODEL'!A:A,'PLAYER MODEL'!D:D),0) | Q15: =IF(J15>0,"Positive 6GW EV",IF(N15>0,"Positive 8GW EV","No clear EV"))
F16: =MAX(0,E16-D16)*4 | G16: =IFERROR(XLOOKUP(B16,'PLAYER MODEL'!A:A,'PLAYER MODEL'!AD:AD),0) | H16: =IFERROR(XLOOKUP(C16,'PLAYER MODEL'!A:A,'PLAYER MODEL'!AD:AD),0) | I16: =H16-G16 | J16: =I16-F16 | K16: =IFERROR(XLOOKUP(B16,'PLAYER MODEL'!A:A,'PLAYER MODEL'!AC:AC),0) | L16: =IFERROR(XLOOKUP(C16,'PLAYER MODEL'!A:A,'PLAYER MODEL'!AC:AC),0) | M16: =L16-K16 | N16: =M16-F16 | O16: =IFERROR(XLOOKUP(C16,'PLAYER MODEL'!A:A,'PLAYER MODEL'!D:D)-XLOOKUP(B16,'PLAYER MODEL'!A:A,'PLAYER MODEL'!D:D),0) | Q16: =IF(J16>0,"Positive 6GW EV",IF(N16>0,"Positive 8GW EV","No clear EV"))
F17: =MAX(0,E17-D17)*4 | G17: =IFERROR(XLOOKUP(B17,'PLAYER MODEL'!A:A,'PLAYER MODEL'!AD:AD),0) | H17: =IFERROR(XLOOKUP(C17,'PLAYER MODEL'!A:A,'PLAYER MODEL'!AD:AD),0) | I17: =H17-G17 | J17: =I17-F17 | K17: =IFERROR(XLOOKUP(B17,'PLAYER MODEL'!A:A,'PLAYER MODEL'!AC:AC),0) | L17: =IFERROR(XLOOKUP(C17,'PLAYER MODEL'!A:A,'PLAYER MODEL'!AC:AC),0) | M17: =L17-K17 | N17: =M17-F17 | O17: =IFERROR(XLOOKUP(C17,'PLAYER MODEL'!A:A,'PLAYER MODEL'!D:D)-XLOOKUP(B17,'PLAYER MODEL'!A:A,'PLAYER MODEL'!D:D),0) | Q17: =IF(J17>0,"Positive 6GW EV",IF(N17>0,"Positive 8GW EV","No clear EV"))
... F105: =MAX(0,E105-D105)*4 | G105: =IFERROR(XLOOKUP(B105,'PLAYER MODEL'!A:A,'PLAYER MODEL'!AD:AD),0) | H105: =IFERROR(XLOOKUP(C105,'PLAYER MODEL'!A:A,'PLAYER MODEL'!AD:AD),0) | I105: =H105-G105 | J105: =I105-F105 | K105: =IFERROR(XLOOKUP(B105,'PLAYER MODEL'!A:A,'PLAYER MODEL'!AC:AC),0) | L105: =IFERROR(XLOOKUP(C105,'PLAYER MODEL'!A:A,'PLAYER MODEL'!AC:AC),0) | M105: =L105-K105 | N105: =M105-F105 | O105: =IFERROR(XLOOKUP(C105,'PLAYER MODEL'!A:A,'PLAYER MODEL'!D:D)-XLOOKUP(B105,'PLAYER MODEL'!A:A,'PLAYER MODEL'!D:D),0) | Q105: =IF(J105>0,"Positive 6GW EV",IF(N105>0,"Positive 8GW EV","No clear EV"))

Sheet CAPTAINCY
A1: Captaincy Probability Board
A2: Formula-driven decision support — not an official FPL prediction.
A3: Captain probability is a decision aid, not a claim of statistical certainty. It allocates a relative probability across the eligible player pool based on attacking ceiling, expected minutes and fixture.
A5: Rank | B5: Player | C5: Club | D5: Pos | E5: GW1 xP | F5: Attacking ceiling | G5: Minutes confidence | H5: Fixture factor | I5: Captain Score | J5: Captain Probability | K5: Reason
A6: 1 | B6: =IFERROR(INDEX('PLAYER MODEL'!A:A,MATCH(LARGE('PLAYER MODEL'!AG:AG,1),'PLAYER MODEL'!AG:AG,0)),"") | C6: =IFERROR(XLOOKUP(B6,'PLAYER MODEL'!A:A,'PLAYER MODEL'!B:B),"") | D6: =IFERROR(XLOOKUP(B6,'PLAYER MODEL'!A:A,'PLAYER MODEL'!C:C),"") | E6: =IFERROR(XLOOKUP(B6,'PLAYER MODEL'!A:A,'PLAYER MODEL'!U:U),0) | F6: =IFERROR(XLOOKUP(B6,'PLAYER MODEL'!A:A,'PLAYER MODEL'!AG:AG),0) | G6: =IFERROR(XLOOKUP(B6,'PLAYER MODEL'!A:A,'PLAYER MODEL'!R:R),0) | H6: =IFERROR(1+(3-XLOOKUP(B6,'WEEKLY INPUT'!A:A,'WEEKLY INPUT'!R:R))*0.10,1) | I6: =F6*G6*H6 | J6: =IFERROR(I6/SUM($I$6:$I$20),0) | K6: =IF(J6=MAX($J$6:$J$20),"Top captain candidate","Compare with fixture/team news")
A7: 2 | B7: =IFERROR(INDEX('PLAYER MODEL'!A:A,MATCH(LARGE('PLAYER MODEL'!AG:AG,2),'PLAYER MODEL'!AG:AG,0)),"") | C7: =IFERROR(XLOOKUP(B7,'PLAYER MODEL'!A:A,'PLAYER MODEL'!B:B),"") | D7: =IFERROR(XLOOKUP(B7,'PLAYER MODEL'!A:A,'PLAYER MODEL'!C:C),"") | E7: =IFERROR(XLOOKUP(B7,'PLAYER MODEL'!A:A,'PLAYER MODEL'!U:U),0) | F7: =IFERROR(XLOOKUP(B7,'PLAYER MODEL'!A:A,'PLAYER MODEL'!AG:AG),0) | G7: =IFERROR(XLOOKUP(B7,'PLAYER MODEL'!A:A,'PLAYER MODEL'!R:R),0) | H7: =IFERROR(1+(3-XLOOKUP(B7,'WEEKLY INPUT'!A:A,'WEEKLY INPUT'!R:R))*0.10,1) | I7: =F7*G7*H7 | J7: =IFERROR(I7/SUM($I$6:$I$20),0) | K7: =IF(J7=MAX($J$6:$J$20),"Top captain candidate","Compare with fixture/team news")
A8: 3 | B8: =IFERROR(INDEX('PLAYER MODEL'!A:A,MATCH(LARGE('PLAYER MODEL'!AG:AG,3),'PLAYER MODEL'!AG:AG,0)),"") | C8: =IFERROR(XLOOKUP(B8,'PLAYER MODEL'!A:A,'PLAYER MODEL'!B:B),"") | D8: =IFERROR(XLOOKUP(B8,'PLAYER MODEL'!A:A,'PLAYER MODEL'!C:C),"") | E8: =IFERROR(XLOOKUP(B8,'PLAYER MODEL'!A:A,'PLAYER MODEL'!U:U),0) | F8: =IFERROR(XLOOKUP(B8,'PLAYER MODEL'!A:A,'PLAYER MODEL'!AG:AG),0) | G8: =IFERROR(XLOOKUP(B8,'PLAYER MODEL'!A:A,'PLAYER MODEL'!R:R),0) | H8: =IFERROR(1+(3-XLOOKUP(B8,'WEEKLY INPUT'!A:A,'WEEKLY INPUT'!R:R))*0.10,1) | I8: =F8*G8*H8 | J8: =IFERROR(I8/SUM($I$6:$I$20),0) | K8: =IF(J8=MAX($J$6:$J$20),"Top captain candidate","Compare with fixture/team news")
A9: 4 | B9: =IFERROR(INDEX('PLAYER MODEL'!A:A,MATCH(LARGE('PLAYER MODEL'!AG:AG,4),'PLAYER MODEL'!AG:AG,0)),"") | C9: =IFERROR(XLOOKUP(B9,'PLAYER MODEL'!A:A,'PLAYER MODEL'!B:B),"") | D9: =IFERROR(XLOOKUP(B9,'PLAYER MODEL'!A:A,'PLAYER MODEL'!C:C),"") | E9: =IFERROR(XLOOKUP(B9,'PLAYER MODEL'!A:A,'PLAYER MODEL'!U:U),0) | F9: =IFERROR(XLOOKUP(B9,'PLAYER MODEL'!A:A,'PLAYER MODEL'!AG:AG),0) | G9: =IFERROR(XLOOKUP(B9,'PLAYER MODEL'!A:A,'PLAYER MODEL'!R:R),0) | H9: =IFERROR(1+(3-XLOOKUP(B9,'WEEKLY INPUT'!A:A,'WEEKLY INPUT'!R:R))*0.10,1) | I9: =F9*G9*H9 | J9: =IFERROR(I9/SUM($I$6:$I$20),0) | K9: =IF(J9=MAX($J$6:$J$20),"Top captain candidate","Compare with fixture/team news")
A10: 5 | B10: =IFERROR(INDEX('PLAYER MODEL'!A:A,MATCH(LARGE('PLAYER MODEL'!AG:AG,5),'PLAYER MODEL'!AG:AG,0)),"") | C10: =IFERROR(XLOOKUP(B10,'PLAYER MODEL'!A:A,'PLAYER MODEL'!B:B),"") | D10: =IFERROR(XLOOKUP(B10,'PLAYER MODEL'!A:A,'PLAYER MODEL'!C:C),"") | E10: =IFERROR(XLOOKUP(B10,'PLAYER MODEL'!A:A,'PLAYER MODEL'!U:U),0) | F10: =IFERROR(XLOOKUP(B10,'PLAYER MODEL'!A:A,'PLAYER MODEL'!AG:AG),0) | G10: =IFERROR(XLOOKUP(B10,'PLAYER MODEL'!A:A,'PLAYER MODEL'!R:R),0) | H10: =IFERROR(1+(3-XLOOKUP(B10,'WEEKLY INPUT'!A:A,'WEEKLY INPUT'!R:R))*0.10,1) | I10: =F10*G10*H10 | J10: =IFERROR(I10/SUM($I$6:$I$20),0) | K10: =IF(J10=MAX($J$6:$J$20),"Top captain candidate","Compare with fixture/team news")
A11: 6 | B11: =IFERROR(INDEX('PLAYER MODEL'!A:A,MATCH(LARGE('PLAYER MODEL'!AG:AG,6),'PLAYER MODEL'!AG:AG,0)),"") | C11: =IFERROR(XLOOKUP(B11,'PLAYER MODEL'!A:A,'PLAYER MODEL'!B:B),"") | D11: =IFERROR(XLOOKUP(B11,'PLAYER MODEL'!A:A,'PLAYER MODEL'!C:C),"") | E11: =IFERROR(XLOOKUP(B11,'PLAYER MODEL'!A:A,'PLAYER MODEL'!U:U),0) | F11: =IFERROR(XLOOKUP(B11,'PLAYER MODEL'!A:A,'PLAYER MODEL'!AG:AG),0) | G11: =IFERROR(XLOOKUP(B11,'PLAYER MODEL'!A:A,'PLAYER MODEL'!R:R),0) | H11: =IFERROR(1+(3-XLOOKUP(B11,'WEEKLY INPUT'!A:A,'WEEKLY INPUT'!R:R))*0.10,1) | I11: =F11*G11*H11 | J11: =IFERROR(I11/SUM($I$6:$I$20),0) | K11: =IF(J11=MAX($J$6:$J$20),"Top captain candidate","Compare with fixture/team news")
A12: 7 | B12: =IFERROR(INDEX('PLAYER MODEL'!A:A,MATCH(LARGE('PLAYER MODEL'!AG:AG,7),'PLAYER MODEL'!AG:AG,0)),"") | C12: =IFERROR(XLOOKUP(B12,'PLAYER MODEL'!A:A,'PLAYER MODEL'!B:B),"") | D12: =IFERROR(XLOOKUP(B12,'PLAYER MODEL'!A:A,'PLAYER MODEL'!C:C),"") | E12: =IFERROR(XLOOKUP(B12,'PLAYER MODEL'!A:A,'PLAYER MODEL'!U:U),0) | F12: =IFERROR(XLOOKUP(B12,'PLAYER MODEL'!A:A,'PLAYER MODEL'!AG:AG),0) | G12: =IFERROR(XLOOKUP(B12,'PLAYER MODEL'!A:A,'PLAYER MODEL'!R:R),0) | H12: =IFERROR(1+(3-XLOOKUP(B12,'WEEKLY INPUT'!A:A,'WEEKLY INPUT'!R:R))*0.10,1) | I12: =F12*G12*H12 | J12: =IFERROR(I12/SUM($I$6:$I$20),0) | K12: =IF(J12=MAX($J$6:$J$20),"Top captain candidate","Compare with fixture/team news")
A13: 8 | B13: =IFERROR(INDEX('PLAYER MODEL'!A:A,MATCH(LARGE('PLAYER MODEL'!AG:AG,8),'PLAYER MODEL'!AG:AG,0)),"") | C13: =IFERROR(XLOOKUP(B13,'PLAYER MODEL'!A:A,'PLAYER MODEL'!B:B),"") | D13: =IFERROR(XLOOKUP(B13,'PLAYER MODEL'!A:A,'PLAYER MODEL'!C:C),"") | E13: =IFERROR(XLOOKUP(B13,'PLAYER MODEL'!A:A,'PLAYER MODEL'!U:U),0) | F13: =IFERROR(XLOOKUP(B13,'PLAYER MODEL'!A:A,'PLAYER MODEL'!AG:AG),0) | G13: =IFERROR(XLOOKUP(B13,'PLAYER MODEL'!A:A,'PLAYER MODEL'!R:R),0) | H13: =IFERROR(1+(3-XLOOKUP(B13,'WEEKLY INPUT'!A:A,'WEEKLY INPUT'!R:R))*0.10,1) | I13: =F13*G13*H13 | J13: =IFERROR(I13/SUM($I$6:$I$20),0) | K13: =IF(J13=MAX($J$6:$J$20),"Top captain candidate","Compare with fixture/team news")
A14: 9 | B14: =IFERROR(INDEX('PLAYER MODEL'!A:A,MATCH(LARGE('PLAYER MODEL'!AG:AG,9),'PLAYER MODEL'!AG:AG,0)),"") | C14: =IFERROR(XLOOKUP(B14,'PLAYER MODEL'!A:A,'PLAYER MODEL'!B:B),"") | D14: =IFERROR(XLOOKUP(B14,'PLAYER MODEL'!A:A,'PLAYER MODEL'!C:C),"") | E14: =IFERROR(XLOOKUP(B14,'PLAYER MODEL'!A:A,'PLAYER MODEL'!U:U),0) | F14: =IFERROR(XLOOKUP(B14,'PLAYER MODEL'!A:A,'PLAYER MODEL'!AG:AG),0) | G14: =IFERROR(XLOOKUP(B14,'PLAYER MODEL'!A:A,'PLAYER MODEL'!R:R),0) | H14: =IFERROR(1+(3-XLOOKUP(B14,'WEEKLY INPUT'!A:A,'WEEKLY INPUT'!R:R))*0.10,1) | I14: =F14*G14*H14 | J14: =IFERROR(I14/SUM($I$6:$I$20),0) | K14: =IF(J14=MAX($J$6:$J$20),"Top captain candidate","Compare with fixture/team news")
A15: 10 | B15: =IFERROR(INDEX('PLAYER MODEL'!A:A,MATCH(LARGE('PLAYER MODEL'!AG:AG,10),'PLAYER MODEL'!AG:AG,0)),"") | C15: =IFERROR(XLOOKUP(B15,'PLAYER MODEL'!A:A,'PLAYER MODEL'!B:B),"") | D15: =IFERROR(XLOOKUP(B15,'PLAYER MODEL'!A:A,'PLAYER MODEL'!C:C),"") | E15: =IFERROR(XLOOKUP(B15,'PLAYER MODEL'!A:A,'PLAYER MODEL'!U:U),0) | F15: =IFERROR(XLOOKUP(B15,'PLAYER MODEL'!A:A,'PLAYER MODEL'!AG:AG),0) | G15: =IFERROR(XLOOKUP(B15,'PLAYER MODEL'!A:A,'PLAYER MODEL'!R:R),0) | H15: =IFERROR(1+(3-XLOOKUP(B15,'WEEKLY INPUT'!A:A,'WEEKLY INPUT'!R:R))*0.10,1) | I15: =F15*G15*H15 | J15: =IFERROR(I15/SUM($I$6:$I$20),0) | K15: =IF(J15=MAX($J$6:$J$20),"Top captain candidate","Compare with fixture/team news")
A16: 11 | B16: =IFERROR(INDEX('PLAYER MODEL'!A:A,MATCH(LARGE('PLAYER MODEL'!AG:AG,11),'PLAYER MODEL'!AG:AG,0)),"") | C16: =IFERROR(XLOOKUP(B16,'PLAYER MODEL'!A:A,'PLAYER MODEL'!B:B),"") | D16: =IFERROR(XLOOKUP(B16,'PLAYER MODEL'!A:A,'PLAYER MODEL'!C:C),"") | E16: =IFERROR(XLOOKUP(B16,'PLAYER MODEL'!A:A,'PLAYER MODEL'!U:U),0) | F16: =IFERROR(XLOOKUP(B16,'PLAYER MODEL'!A:A,'PLAYER MODEL'!AG:AG),0) | G16: =IFERROR(XLOOKUP(B16,'PLAYER MODEL'!A:A,'PLAYER MODEL'!R:R),0) | H16: =IFERROR(1+(3-XLOOKUP(B16,'WEEKLY INPUT'!A:A,'WEEKLY INPUT'!R:R))*0.10,1) | I16: =F16*G16*H16 | J16: =IFERROR(I16/SUM($I$6:$I$20),0) | K16: =IF(J16=MAX($J$6:$J$20),"Top captain candidate","Compare with fixture/team news")
A17: 12 | B17: =IFERROR(INDEX('PLAYER MODEL'!A:A,MATCH(LARGE('PLAYER MODEL'!AG:AG,12),'PLAYER MODEL'!AG:AG,0)),"") | C17: =IFERROR(XLOOKUP(B17,'PLAYER MODEL'!A:A,'PLAYER MODEL'!B:B),"") | D17: =IFERROR(XLOOKUP(B17,'PLAYER MODEL'!A:A,'PLAYER MODEL'!C:C),"") | E17: =IFERROR(XLOOKUP(B17,'PLAYER MODEL'!A:A,'PLAYER MODEL'!U:U),0) | F17: =IFERROR(XLOOKUP(B17,'PLAYER MODEL'!A:A,'PLAYER MODEL'!AG:AG),0) | G17: =IFERROR(XLOOKUP(B17,'PLAYER MODEL'!A:A,'PLAYER MODEL'!R:R),0) | H17: =IFERROR(1+(3-XLOOKUP(B17,'WEEKLY INPUT'!A:A,'WEEKLY INPUT'!R:R))*0.10,1) | I17: =F17*G17*H17 | J17: =IFERROR(I17/SUM($I$6:$I$20),0) | K17: =IF(J17=MAX($J$6:$J$20),"Top captain candidate","Compare with fixture/team news")
A18: 13 | B18: =IFERROR(INDEX('PLAYER MODEL'!A:A,MATCH(LARGE('PLAYER MODEL'!AG:AG,13),'PLAYER MODEL'!AG:AG,0)),"") | C18: =IFERROR(XLOOKUP(B18,'PLAYER MODEL'!A:A,'PLAYER MODEL'!B:B),"") | D18: =IFERROR(XLOOKUP(B18,'PLAYER MODEL'!A:A,'PLAYER MODEL'!C:C),"") | E18: =IFERROR(XLOOKUP(B18,'PLAYER MODEL'!A:A,'PLAYER MODEL'!U:U),0) | F18: =IFERROR(XLOOKUP(B18,'PLAYER MODEL'!A:A,'PLAYER MODEL'!AG:AG),0) | G18: =IFERROR(XLOOKUP(B18,'PLAYER MODEL'!A:A,'PLAYER MODEL'!R:R),0) | H18: =IFERROR(1+(3-XLOOKUP(B18,'WEEKLY INPUT'!A:A,'WEEKLY INPUT'!R:R))*0.10,1) | I18: =F18*G18*H18 | J18: =IFERROR(I18/SUM($I$6:$I$20),0) | K18: =IF(J18=MAX($J$6:$J$20),"Top captain candidate","Compare with fixture/team news")
A19: 14 | B19: =IFERROR(INDEX('PLAYER MODEL'!A:A,MATCH(LARGE('PLAYER MODEL'!AG:AG,14),'PLAYER MODEL'!AG:AG,0)),"") | C19: =IFERROR(XLOOKUP(B19,'PLAYER MODEL'!A:A,'PLAYER MODEL'!B:B),"") | D19: =IFERROR(XLOOKUP(B19,'PLAYER MODEL'!A:A,'PLAYER MODEL'!C:C),"") | E19: =IFERROR(XLOOKUP(B19,'PLAYER MODEL'!A:A,'PLAYER MODEL'!U:U),0) | F19: =IFERROR(XLOOKUP(B19,'PLAYER MODEL'!A:A,'PLAYER MODEL'!AG:AG),0) | G19: =IFERROR(XLOOKUP(B19,'PLAYER MODEL'!A:A,'PLAYER MODEL'!R:R),0) | H19: =IFERROR(1+(3-XLOOKUP(B19,'WEEKLY INPUT'!A:A,'WEEKLY INPUT'!R:R))*0.10,1) | I19: =F19*G19*H19 | J19: =IFERROR(I19/SUM($I$6:$I$20),0) | K19: =IF(J19=MAX($J$6:$J$20),"Top captain candidate","Compare with fixture/team news")
A20: 15 | B20: =IFERROR(INDEX('PLAYER MODEL'!A:A,MATCH(LARGE('PLAYER MODEL'!AG:AG,15),'PLAYER MODEL'!AG:AG,0)),"") | C20: =IFERROR(XLOOKUP(B20,'PLAYER MODEL'!A:A,'PLAYER MODEL'!B:B),"") | D20: =IFERROR(XLOOKUP(B20,'PLAYER MODEL'!A:A,'PLAYER MODEL'!C:C),"") | E20: =IFERROR(XLOOKUP(B20,'PLAYER MODEL'!A:A,'PLAYER MODEL'!U:U),0) | F20: =IFERROR(XLOOKUP(B20,'PLAYER MODEL'!A:A,'PLAYER MODEL'!AG:AG),0) | G20: =IFERROR(XLOOKUP(B20,'PLAYER MODEL'!A:A,'PLAYER MODEL'!R:R),0) | H20: =IFERROR(1+(3-XLOOKUP(B20,'WEEKLY INPUT'!A:A,'WEEKLY INPUT'!R:R))*0.10,1) | I20: =F20*G20*H20 | J20: =IFERROR(I20/SUM($I$6:$I$20),0) | K20: =IF(J20=MAX($J$6:$J$20),"Top captain candidate","Compare with fixture/team news")

Sheet CHIP PLANNER
A1: Chip Timing Planner
A2: Formula-driven decision support — not an official FPL prediction.
A3: Score each Gameweek manually after reviewing blanks/doubles, squad coverage and the 8GW projection. The sheet provides a framework rather than pretending the optimal chip week can be known months ahead.
A5: GW | B5: Blank GW score | C5: Double GW score | D5: Fixture swing score | E5: Squad coverage | F5: Captain upside | G5: Bench upside | H5: Wildcard need | I5: Free Hit need | J5: Triple Captain need | K5: Bench Boost need | L5: Overall chip opportunity | M5: Notes
A6: 1 | L6: =SUM(B6:K6)
A7: 2 | L7: =SUM(B7:K7)
A8: 3 | L8: =SUM(B8:K8)
A9: 4 | L9: =SUM(B9:K9)
A10: 5 | L10: =SUM(B10:K10)
A11: 6 | L11: =SUM(B11:K11)
A12: 7 | L12: =SUM(B12:K12)
A13: 8 | L13: =SUM(B13:K13)
A14: 9 | L14: =SUM(B14:K14)
A15: 10 | L15: =SUM(B15:K15)
A16: 11 | L16: =SUM(B16:K16)
A17: 12 | L17: =SUM(B17:K17)
... A43: 38 | L43: =SUM(B43:K43)
A45: Rule reminder | B45: 2026/27 has two sets of Wildcard, Free Hit, Triple Captain and Bench Boost; the first set must be used before the GW19 deadline. Only one chip can be used in a Gameweek.

Sheet WEEKLY REVIEW
A1: Weekly Review & Model Calibration
A5: GW | B5: Projected points | C5: Actual points | D5: Variance | E5: Captain projected | F5: Captain actual | G5: Captain variance | H5: Transfer EV taken | I5: Rank | J5: What did the model miss?
A6: 1 | D6: =IF(OR(B6="",C6=""),"",C6-B6) | G6: =IF(OR(E6="",F6=""),"",F6-E6)
A7: 2 | D7: =IF(OR(B7="",C7=""),"",C7-B7) | G7: =IF(OR(E7="",F7=""),"",F7-E7)
A8: 3 | D8: =IF(OR(B8="",C8=""),"",C8-B8) | G8: =IF(OR(E8="",F8=""),"",F8-E8)
A9: 4 | D9: =IF(OR(B9="",C9=""),"",C9-B9) | G9: =IF(OR(E9="",F9=""),"",F9-E9)
A10: 5 | D10: =IF(OR(B10="",C10=""),"",C10-B10) | G10: =IF(OR(E10="",F10=""),"",F10-E10)
A11: 6 | D11: =IF(OR(B11="",C11=""),"",C11-B11) | G11: =IF(OR(E11="",F11=""),"",F11-E11)
A12: 7 | D12: =IF(OR(B12="",C12=""),"",C12-B12) | G12: =IF(OR(E12="",F12=""),"",F12-E12)
A13: 8 | D13: =IF(OR(B13="",C13=""),"",C13-B13) | G13: =IF(OR(E13="",F13=""),"",F13-E13)
A14: 9 | D14: =IF(OR(B14="",C14=""),"",C14-B14) | G14: =IF(OR(E14="",F14=""),"",F14-E14)
A15: 10 | D15: =IF(OR(B15="",C15=""),"",C15-B15) | G15: =IF(OR(E15="",F15=""),"",F15-E15)
A16: 11 | D16: =IF(OR(B16="",C16=""),"",C16-B16) | G16: =IF(OR(E16="",F16=""),"",F16-E16)
A17: 12 | D17: =IF(OR(B17="",C17=""),"",C17-B17) | G17: =IF(OR(E17="",F17=""),"",F17-E17)
... A43: 38 | D43: =IF(OR(B43="",C43=""),"",C43-B43) | G43: =IF(OR(E43="",F43=""),"",F43-E43)

Sheet MODEL ARCHITECTURE
A1: Layer | B1: Status | C1: Purpose
A2: Official FPL data | B2: Automated | C2: Players, prices, ownership, form, xG/xA/xGI, availability, fixtures, FDR, Gameweeks and live/history data.
A3: Historical data | B3: Automated | C3: Keep prior refreshes so model accuracy can be measured and weights recalibrated.
A4: Minutes/team news | B4: Manual | C4: Projected minutes, start probability, rotation, injuries, tactical changes and set-piece responsibility.
A5: 8-GW projection | B5: Formula | C5: Expected points by Gameweek using minutes, attacking involvement, defensive contribution, fixture adjustment and horizon decay.
A6: Transfer EV | B6: Formula | C6: 6-GW and 8-GW expected gain from IN vs OUT after transfer-hit cost.
A7: Captaincy | B7: Formula | C7: Relative captain score/probability using expected output, attacking ceiling and availability.
A8: XI optimiser | B8: Formula | C8: Ranks legal formation options and selects the strongest expected XI from the user's squad.
A9: Chip planner | B9: Formula + review | C9: Scores blank/double weeks, fixture swings, squad coverage, captain upside and bench upside.
A10: Calibration | B10: Formula + review | C10: Actual minus projected points, allowing repeated model errors to be identified.
